Workbook

Sheet Inventory
A1: Geography | H1: Priority | M1: Market evidence | Z1: Evidence quality | AD1: Page plan
A2: State | B2: Region | C2: County / borough / statistical area | D2: GEOID (FIPS) | E2: Census geography name | F2: Record type | G2: Statistical areas attached / hub attached to | H2: Tier | I2: Rationale | J2: Build wave | K2: Page status | L2: Publish decision | M2: Population | N2: Median owner-occupied home value ($) | O2: Housing units (all) | P2: Occupied housing units | Q2: Owner-occupied units | R2: Homeownership rate (owner ÷ occupied) | S2: Owner households age 65+ | T2: Owners 65+ share | U2: 1–4 unit share of all housing stock | V2: Median year built | W2: Median household income ($) | X2: Annual homes sold | Y2: Investor purchase share | Z2: Missing-data flags | AA2: Source | AB2: Measurement period | AC2: Source URL | AD2: Existing URLs (live sitemap) | AE2: Proposed hub URL | AF2: Parent hub | AG2: Candidate city / neighborhood pages
A3: PA | B3: Lehigh Valley | C3: Lehigh County | D3: 42077 | E3: Lehigh County, PA | F3: page | H3: Existing core | I3: Existing footprint; Allentown pages already rank; attach to hierarchy, no URL moves | J3: Wave 1 | K3: Existing pages (attach to hierarchy) | L3: Wave 1: create county record, attach existing pages, publish county hub only if it adds distinct value | M3: 378792 | N3: 300400 | O3: 151220 | P3: 144386 | Q3: 94675 | R3: =IF(AND(ISNUMBER(Q3),P3>0),Q3/P3,"") -> 0.65570762 | S3: 30127 | T3: =IF(AND(ISNUMBER(S3),Q3>0),S3/Q3,"") -> 0.31821495 | U3: =IF(AND(ISNUMBER(O3),O3>0),125372/O3,"") -> 0.82907023 | V3: 1968 | W3: 80079 | Z3: Annual homes sold not populated — source: Redfin Data Center county-level housing market download (homes sold, monthly); record period when filled; Investor purchase share not populated — Redfin/ATTOM investor data uses metro definitions; store only if the geography matches this row, else leave blank and note the metro figure in Rationale | AA3: US Census Bureau ACS via Census Reporter | AB3: ACS 2024 5-year (2020–2024) | AC3: https://censusreporter.org/profiles/05000US42077/ | AD3: https://www.clearedgehomebuyers.com/locations/lehigh-valley; https://www.clearedgehomebuyers.com/locations/allentown | AE3: https://www.clearedgehomebuyers.com/locations/pennsylvania/lehigh-county | AF3: /locations/lehigh-valley | AG3: Allentown (existing), Emmaus, Whitehall
A4: PA | B4: Lehigh Valley | C4: Northampton County | D4: 42095 | E4: Northampton County, PA | F4: page | H4: Existing core | I4: Existing footprint; Bethlehem and Easton pages rank and produced attributed leads | J4: Wave 1 | K4: Existing pages (attach to hierarchy) | L4: Wave 1: create county record, attach existing pages, publish county hub only if it adds distinct value | M4: 318580 | N4: 308600 | O4: 129448 | P4: 122624 | Q4: 87201 | R4: =IF(AND(ISNUMBER(Q4),P4>0),Q4/P4,"") -> 0.71112507 | S4: 30618 | T4: =IF(AND(ISNUMBER(S4),Q4>0),S4/Q4,"") -> 0.35111983 | U4: =IF(AND(ISNUMBER(O4),O4>0),112147/O4,"") -> 0.86634788 | V4: 1971 | W4: 89184 | Z4: Annual homes sold not populated — source: Redfin Data Center county-level housing market download (homes sold, monthly); record period when filled; Investor purchase share not populated — Redfin/ATTOM investor data uses metro definitions; store only if the geography matches this row, else leave blank and note the metro figure in Rationale | AA4: US Census Bureau ACS via Census Reporter | AB4: ACS 2024 5-year (2020–2024) | AC4: https://censusreporter.org/profiles/05000US42095/ | AD4: https://www.clearedgehomebuyers.com/locations/lehigh-valley; https://www.clearedgehomebuyers.com/locations/bethlehem; https://www.clearedgehomebuyers.com/locations/easton | AE4: https://www.clearedgehomebuyers.com/locations/pennsylvania/northampton-county | AF4: /locations/lehigh-valley | AG4: Bethlehem (existing), Easton (existing), Nazareth
A5: PA | B5: Berks | C5: Berks County | D5: 42011 | E5: Berks County, PA | F5: page | H5: Existing core | I5: Existing footprint; Reading inherited page hit position 2 in week three | J5: Wave 1 | K5: Existing pages (attach to hierarchy) | L5: Wave 1: create county record, attach existing pages, publish county hub only if it adds distinct value | M5: 433015 | N5: 257300 | O5: 171580 | P5: 163236 | Q5: 116334 | R5: =IF(AND(ISNUMBER(Q5),P5>0),Q5/P5,"") -> 0.71267367 | S5: 37215 | T5: =IF(AND(ISNUMBER(S5),Q5>0),S5/Q5,"") -> 0.31989788 | U5: =IF(AND(ISNUMBER(O5),O5>0),149447/O5,"") -> 0.87100478 | V5: 1969 | W5: 79777 | Z5: Annual homes sold not populated — source: Redfin Data Center county-level housing market download (homes sold, monthly); record period when filled; Investor purchase share not populated — Redfin/ATTOM investor data uses metro definitions; store only if the geography matches this row, else leave blank and note the metro figure in Rationale | AA5: US Census Bureau ACS via Census Reporter | AB5: ACS 2024 5-year (2020–2024) | AC5: https://censusreporter.org/profiles/05000US42011/ | AD5: https://www.clearedgehomebuyers.com/locations/reading | AE5: https://www.clearedgehomebuyers.com/locations/pennsylvania/berks-county | AF5: /locations/pennsylvania | AG5: Reading (existing), Wyomissing, Boyertown
A6: PA | B6: NEPA | C6: Lackawanna County | D6: 42069 | E6: Lackawanna County, PA | F6: page | H6: Existing core | I6: Existing footprint; Scranton cluster ranks; low price points limit fee size | J6: Wave 1 | K6: Existing pages (attach to hierarchy) | L6: Wave 1: create county record, attach existing pages, publish county hub only if it adds distinct value | M6: 216146 | N6: 201800 | O6: 100177 | P6: 88263 | Q6: 57744 | R6: =IF(AND(ISNUMBER(Q6),P6>0),Q6/P6,"") -> 0.65422657 | S6: 20966 | T6: =IF(AND(ISNUMBER(S6),Q6>0),S6/Q6,"") -> 0.36308534 | U6: =IF(AND(ISNUMBER(O6),O6>0),89089/O6,"") -> 0.88931591 | V6: 1955 | W6: 66223 | Z6: Annual homes sold not populated — source: Redfin Data Center county-level housing market download (homes sold, monthly); record period when filled; Investor purchase share not populated — Redfin/ATTOM investor data uses metro definitions; store only if the geography matches this row, else leave blank and note the metro figure in Rationale | AA6: US Census Bureau ACS via Census Reporter | AB6: ACS 2024 5-year (2020–2024) | AC6: https://censusreporter.org/profiles/05000US42069/ | AD6: https://www.clearedgehomebuyers.com/locations/nepa; https://www.clearedgehomebuyers.com/locations/scranton; https://www.clearedgehomebuyers.com/locations/dunmore; https://www.clearedgehomebuyers.com/locations/carbondale | AE6: https://www.clearedgehomebuyers.com/locations/pennsylvania/lackawanna-county | AF6: /locations/nepa | AG6: Scranton, Dunmore, Carbondale (all existing)
A7: PA | B7: NEPA | C7: Luzerne County | D7: 42079 | E7: Luzerne County, PA | F7: page | H7: Existing core | I7: Existing footprint; five city pages live; low price points limit fee size | J7: Wave 1 | K7: Existing pages (attach to hierarchy) | L7: Wave 1: create county record, attach existing pages, publish county hub only if it adds distinct value | M7: 327675 | N7: 174100 | O7: 151287 | P7: 135055 | Q7: 91565 | R7: =IF(AND(ISNUMBER(Q7),P7>0),Q7/P7,"") -> 0.67798304 | S7: 32913 | T7: =IF(AND(ISNUMBER(S7),Q7>0),S7/Q7,"") -> 0.35944957 | U7: =IF(AND(ISNUMBER(O7),O7>0),134308/O7,"") -> 0.8877696 | V7: 1960 | W7: 63691 | Z7: Annual homes sold not populated — source: Redfin Data Center county-level housing market download (homes sold, monthly); record period when filled; Investor purchase share not populated — Redfin/ATTOM investor data uses metro definitions; store only if the geography matches this row, else leave blank and note the metro figure in Rationale | AA7: US Census Bureau ACS via Census Reporter | AB7: ACS 2024 5-year (2020–2024) | AC7: https://censusreporter.org/profiles/05000US42079/ | AD7: https://www.clearedgehomebuyers.com/locations/nepa; https://www.clearedgehomebuyers.com/locations/wilkes-barre; https://www.clearedgehomebuyers.com/locations/kingston; https://www.clearedgehomebuyers.com/locations/nanticoke; https://www.clearedgehomebuyers.com/locations/pittston; https://www.clearedgehomebuyers.com/locations/hazleton | AE7: https://www.clearedgehomebuyers.com/locations/pennsylvania/luzerne-county | AF7: /locations/nepa | AG7: Wilkes-Barre, Kingston, Nanticoke, Pittston, Hazleton (all existing)
A8: PA | B8: Poconos | C8: Monroe County | D8: 42089 | E8: Monroe County, PA | F8: page | H8: Existing core | I8: Existing footprint; four Pocono pages live; second-home and inherited-cabin demand | J8: Wave 1 | K8: Existing pages (attach to hierarchy) | L8: Wave 1: create county record, attach existing pages, publish county hub only if it adds distinct value | M8: 167515 | N8: 267600 | O8: 79607 | P8: 61212 | Q8: 49111 | R8: =IF(AND(ISNUMBER(Q8),P8>0),Q8/P8,"") -> 0.80231 | S8: 16053 | T8: =IF(AND(ISNUMBER(S8),Q8>0),S8/Q8,"") -> 0.32687178 | U8: =IF(AND(ISNUMBER(O8),O8>0),74307/O8,"") -> 0.93342294 | V8: 1984 | W8: 83565 | Z8: Annual homes sold not populated — source: Redfin Data Center county-level housing market download (homes sold, monthly); record period when filled; Investor purchase share not populated — Redfin/ATTOM investor data uses metro definitions; store only if the geography matches this row, else leave blank and note the metro figure in Rationale | AA8: US Census Bureau ACS via Census Reporter | AB8: ACS 2024 5-year (2020–2024) | AC8: https://censusreporter.org/profiles/05000US42089/ | AD8: https://www.clearedgehomebuyers.com/locations/poconos; https://www.clearedgehomebuyers.com/locations/stroudsburg; https://www.clearedgehomebuyers.com/locations/east-stroudsburg; https://www.clearedgehomebuyers.com/locations/tannersville; https://www.clearedgehomebuyers.com/locations/pocono-pines | AE8: https://www.clearedgehomebuyers.com/locations/pennsylvania/monroe-county | AF8: /locations/poconos | AG8: Stroudsburg, East Stroudsburg, Tannersville, Pocono Pines (all existing)
A9: PA | B9: NEPA | C9: Schuylkill County | D9: 42107 | E9: Schuylkill County, PA | F9: page | H9: Existing core | I9: Existing footprint via Pottsville page; very low values | J9: Wave 1 | K9: Existing pages (attach to hierarchy) | L9: Wave 1: create county record, attach existing pages, publish county hub only if it adds distinct value | M9: 143558 | N9: 153000 | O9: 67295 | P9: 57988 | Q9: 44125 | R9: =IF(AND(ISNUMBER(Q9),P9>0),Q9/P9,"") -> 0.7609333 | S9: 15148 | T9: =IF(AND(ISNUMBER(S9),Q9>0),S9/Q9,"") -> 0.34329745 | U9: =IF(AND(ISNUMBER(O9),O9>0),60761/O9,"") -> 0.90290512 | V9: 1946 | W9: 68313 | Z9: Annual homes sold not populated — source: Redfin Data Center county-level housing market download (homes sold, monthly); record period when filled; Investor purchase share not populated — Redfin/ATTOM investor data uses metro definitions; store only if the geography matches this row, else leave blank and note the metro figure in Rationale | AA9: US Census Bureau ACS via Census Reporter | AB9: ACS 2024 5-year (2020–2024) | AC9: https://censusreporter.org/profiles/05000US42107/ | AD9: https://www.clearedgehomebuyers.com/locations/pottsville | AE9: https://www.clearedgehomebuyers.com/locations/pennsylvania/schuylkill-county | AF9: /locations/nepa | AG9: Pottsville (existing)
A10: PA | B10: NEPA | C10: Wayne County | D10: 42127 | E10: Wayne County, PA | F10: page | H10: Existing core | I10: Existing footprint via Honesdale page; rural, lake/second-home stock | J10: Wave 1 | K10: Existing pages (attach to hierarchy) | L10: Wave 1: create county record, attach existing pages, publish county hub only if it adds distinct value | M10: 51262 | N10: 242100 | O10: 32171 | P10: 20877 | Q10: 16811 | R10: =IF(AND(ISNUMBER(Q10),P10>0),Q10/P10,"") -> 0.80524022 | S10: 7146 | T10: =IF(AND(ISNUMBER(S10),Q10>0),S10/Q10,"") -> 0.42507882 | U10: =IF(AND(ISNUMBER(O10),O10>0),28742/O10,"") -> 0.89341332 | V10: 1980 | W10: 62381 | Z10: Annual homes sold not populated — source: Redfin Data Center county-level housing market download (homes sold, monthly); record period when filled; Investor purchase share not populated — Redfin/ATTOM investor data uses metro definitions; store only if the geography matches this row, else leave blank and note the metro figure in Rationale | AA10: US Census Bureau ACS via Census Reporter | AB10: ACS 2024 5-year (2020–2024) | AC10: https://censusreporter.org/profiles/05000US42127/ | AD10: https://www.clearedgehomebuyers.com/locations/honesdale | AE10: https://www.clearedgehomebuyers.com/locations/pennsylvania/wayne-county | AF10: /locations/nepa | AG10: Honesdale (existing)
A11: PA | B11: NEPA | C11: Columbia County | D11: 42037 | E11: Columbia County, PA | F11: page | H11: Existing core | I11: Existing footprint via Bloomsburg page; small market | J11: Wave 1 | K11: Existing pages (attach to hierarchy) | L11: Wave 1: create county record, attach existing pages, publish county hub only if it adds distinct value | M11: 65362 | N11: 206200 | O11: 29824 | P11: 26350 | Q11: 18313 | R11: =IF(AND(ISNUMBER(Q11),P11>0),Q11/P11,"") -> 0.69499051 | S11: 6556 | T11: =IF(AND(ISNUMBER(S11),Q11>0),S11/Q11,"") -> 0.35799705 | U11: =IF(AND(ISNUMBER(O11),O11>0),25133/O11,"") -> 0.84271057 | V11: 1970 | W11: 64644 | Z11: Annual homes sold not populated — source: Redfin Data Center county-level housing market download (homes sold, monthly); record period when filled; Investor purchase share not populated — Redfin/ATTOM investor data uses metro definitions; store only if the geography matches this row, else leave blank and note the metro figure in Rationale | AA11: US Census Bureau ACS via Census Reporter | AB11: ACS 2024 5-year (2020–2024) | AC11: https://censusreporter.org/profiles/05000US42037/ | AD11: https://www.clearedgehomebuyers.com/locations/bloomsburg | AE11: https://www.clearedgehomebuyers.com/locations/pennsylvania/columbia-county | AF11: /locations/nepa | AG11: Bloomsburg (existing)
A12: PA | B12: Philadelphia suburbs | C12: Montgomery County | D12: 42091 | E12: Montgomery County, PA | F12: page | H12: Tier 1 | I12: Source of the most profitable deal to date; high values, deep buyer pool, no page existed | J12: Wave 1 | K12: New hub | L12: Wave 1: publish county/borough hub; city pages only where demand verified | M12: 867573 | N12: 436700 | O12: 350351 | P12: 335505 | Q12: 239495 | R12: =IF(AND(ISNUMBER(Q12),P12>0),Q12/P12,"") -> 0.71383437 | S12: 74564 | T12: =IF(AND(ISNUMBER(S12),Q12>0),S12/Q12,"") -> 0.31133844 | U12: =IF(AND(ISNUMBER(O12),O12>0),280550/O12,"") -> 0.80076837 | V12: 1971 | W12: 113915 | Z12: Annual homes sold not populated — source: Redfin Data Center county-level housing market download (homes sold, monthly); record period when filled; Investor purchase share not populated — Redfin/ATTOM investor data uses metro definitions; store only if the geography matches this row, else leave blank and note the metro figure in Rationale | AA12: US Census Bureau ACS via Census Reporter | AB12: ACS 2024 5-year (2020–2024) | AC12: https://censusreporter.org/profiles/05000US42091/ | AE12: https://www.clearedgehomebuyers.com/locations/pennsylvania/montgomery-county | AF12: /locations/pennsylvania | AG12: Norristown, Pottstown, Lansdale, Abington, Cheltenham, Upper Merion
A13: PA | B13: Philadelphia suburbs | C13: Bucks County | D13: 42017 | E13: Bucks County, PA | F13: page | H13: Tier 1 | I13: High values, aging suburban stock, strong flip resale demand | J13: Wave 1 | K13: New hub | L13: Wave 1: publish county/borough hub; city pages only where demand verified | M13: 647461 | N13: 445700 | O13: 257260 | P13: 249187 | Q13: 193879 | R13: =IF(AND(ISNUMBER(Q13),P13>0),Q13/P13,"") -> 0.77804621 | S13: 64800 | T13: =IF(AND(ISNUMBER(S13),Q13>0),S13/Q13,"") -> 0.33422908 | U13: =IF(AND(ISNUMBER(O13),O13>0),216851/O13,"") -> 0.84292545 | V13: 1975 | W13: 114764 | Z13: Annual homes sold not populated — source: Redfin Data Center county-level housing market download (homes sold, monthly); record period when filled; Investor purchase share not populated — Redfin/ATTOM investor data uses metro definitions; store only if the geography matches this row, else leave blank and note the metro figure in Rationale | AA13: US Census Bureau ACS via Census Reporter | AB13: ACS 2024 5-year (2020–2024) | AC13: https://censusreporter.org/profiles/05000US42017/ | AE13: https://www.clearedgehomebuyers.com/locations/pennsylvania/bucks-county | AF13: /locations/pennsylvania | AG13: Levittown, Bristol, Bensalem, Doylestown, Warminster
A14: PA | B14: Philadelphia suburbs | C14: Delaware County | D14: 42045 | E14: Delaware County, PA | F14: page | H14: Tier 1 | I14: Dense older housing, high investor activity, mid values with big spread variance | J14: Wave 1 | K14: New hub | L14: Wave 1: publish county/borough hub; city pages only where demand verified | M14: 579222 | N14: 332200 | O14: 229715 | P14: 216946 | Q14: 151016 | R14: =IF(AND(ISNUMBER(Q14),P14>0),Q14/P14,"") -> 0.69609949 | S14: 48992 | T14: =IF(AND(ISNUMBER(S14),Q14>0),S14/Q14,"") -> 0.32441596 | U14: =IF(AND(ISNUMBER(O14),O14>0),193622/O14,"") -> 0.84287922 | V14: 1957 | W14: 89546 | Z14: Annual homes sold not populated — source: Redfin Data Center county-level housing market download (homes sold, monthly); record period when filled; Investor purchase share not populated — Redfin/ATTOM investor data uses metro definitions; store only if the geography matches this row, else leave blank and note the metro figure in Rationale | AA14: US Census Bureau ACS via Census Reporter | AB14: ACS 2024 5-year (2020–2024) | AC14: https://censusreporter.org/profiles/05000US42045/ | AE14: https://www.clearedgehomebuyers.com/locations/pennsylvania/delaware-county | AF14: /locations/pennsylvania | AG14: Upper Darby, Chester, Drexel Hill, Media, Springfield
A15: PA | B15: Philadelphia suburbs | C15: Chester County | D15: 42029 | E15: Chester County, PA | F15: page | H15: Tier 1 | I15: Highest SE PA values; fewer distressed properties, larger fees when found | J15: Wave 1 | K15: New hub | L15: Wave 1: publish county/borough hub; city pages only where demand verified | M15: 547840 | N15: 485600 | O15: 212491 | P15: 204774 | Q15: 153693 | R15: =IF(AND(ISNUMBER(Q15),P15>0),Q15/P15,"") -> 0.75054939 | S15: 45658 | T15: =IF(AND(ISNUMBER(S15),Q15>0),S15/Q15,"") -> 0.29707274 | U15: =IF(AND(ISNUMBER(O15),O15>0),177660/O15,"") -> 0.83608247 | V15: 1983 | W15: 127208 | Z15: Annual homes sold not populated — source: Redfin Data Center county-level housing market download (homes sold, monthly); record period when filled; Investor purchase share not populated — Redfin/ATTOM investor data uses metro definitions; store only if the geography matches this row, else leave blank and note the metro figure in Rationale | AA15: US Census Bureau ACS via Census Reporter | AB15: ACS 2024 5-year (2020–2024) | AC15: https://censusreporter.org/profiles/05000US42029/ | AE15: https://www.clearedgehomebuyers.com/locations/pennsylvania/chester-county | AF15: /locations/pennsylvania | AG15: Coatesville, West Chester, Phoenixville, Downingtown
A16: PA | B16: Philadelphia | C16: Philadelphia County | D16: 42101 | E16: Philadelphia County, PA | F16: page | H16: Tier 1 | I16: Largest transaction and investor volume in the footprint; treat as its own region hub | J16: Wave 1 | K16: New hub | L16: Wave 1: publish county/borough hub; city pages only where demand verified | M16: 1579706 | N16: 243100 | O16: 748270 | P16: 679428 | Q16: 351905 | R16: =IF(AND(ISNUMBER(Q16),P16>0),Q16/P16,"") -> 0.51794303 | S16: 110007 | T16: =IF(AND(ISNUMBER(S16),Q16>0),S16/Q16,"") -> 0.31260425 | U16: =IF(AND(ISNUMBER(O16),O16>0),587076/O16,"") -> 0.78457776 | V16: 1949 | W16: 61953 | Z16: Annual homes sold not populated — source: Redfin Data Center county-level housing market download (homes sold, monthly); record period when filled; Investor purchase share not populated — Redfin/ATTOM investor data uses metro definitions; store only if the geography matches this row, else leave blank and note the metro figure in Rationale | AA16: US Census Bureau ACS via Census Reporter | AB16: ACS 2024 5-year (2020–2024) | AC16: https://censusreporter.org/profiles/05000US42101/ | AE16: https://www.clearedgehomebuyers.com/locations/pennsylvania/philadelphia | AF16: /locations/pennsylvania | AG16: Northeast Philadelphia, Germantown, West Philadelphia, South Philadelphia (neighborhood pages, selective)
A17: PA | B17: South Central | C17: Lancaster County | D17: 42071 | E17: Lancaster County, PA | F17: page | H17: Tier 2 | I17: Large, growing market with mid values and active investors | J17: Wave 5 | K17: New hub | L17: Wave 5: publish county/borough hub; city pages only where demand verified | M17: 557931 | N17: 301100 | O17: 219224 | P17: 212748 | Q17: 148550 | R17: =IF(AND(ISNUMBER(Q17),P17>0),Q17/P17,"") -> 0.69824393 | S17: 48872 | T17: =IF(AND(ISNUMBER(S17),Q17>0),S17/Q17,"") -> 0.3289936 | U17: =IF(AND(ISNUMBER(O17),O17>0),183381/O17,"") -> 0.83650057 | V17: 1978 | W17: 86959 | Z17: Annual homes sold not populated — source: Redfin Data Center county-level housing market download (homes sold, monthly); record period when filled; Investor purchase share not populated — Redfin/ATTOM investor data uses metro definitions; store only if the geography matches this row, else leave blank and note the metro figure in Rationale | AA17: US Census Bureau ACS via Census Reporter | AB17: ACS 2024 5-year (2020–2024) | AC17: https://censusreporter.org/profiles/05000US42071/ | AE17: https://www.clearedgehomebuyers.com/locations/pennsylvania/lancaster-county | AF17: /locations/pennsylvania | AG17: Lancaster, Lititz, Ephrata
A18: PA | B18: South Central | C18: York County | D18: 42133 | E18: York County, PA | F18: page | H18: Tier 2 | I18: Mid values, high volume, adjacent to Lancaster | J18: Wave 5 | K18: New hub | L18: Wave 5: publish county/borough hub; city pages only where demand verified | M18: 462924 | N18: 248600 | O18: 189857 | P18: 181583 | Q18: 138624 | R18: =IF(AND(ISNUMBER(Q18),P18>0),Q18/P18,"") -> 0.76341948 | S18: 44040 | T18: =IF(AND(ISNUMBER(S18),Q18>0),S18/Q18,"") -> 0.31769391 | U18: =IF(AND(ISNUMBER(O18),O18>0),167450/O18,"") -> 0.8819796 | V18: 1976 | W18: 84829 | Z18: Annual homes sold not populated — source: Redfin Data Center county-level housing market download (homes sold, monthly); record period when filled; Investor purchase share not populated — Redfin/ATTOM investor data uses metro definitions; store only if the geography matches this row, else leave blank and note the metro figure in Rationale | AA18: US Census Bureau ACS via Census Reporter | AB18: ACS 2024 5-year (2020–2024) | AC18: https://censusreporter.org/profiles/05000US42133/ | AE18: https://www.clearedgehomebuyers.com/locations/pennsylvania/york-county | AF18: /locations/pennsylvania | AG18: York, Hanover
A19: PA | B19: South Central | C19: Dauphin County | D19: 42043 | E19: Dauphin County, PA | F19: page | H19: Tier 2 | I19: Harrisburg metro; state-capital employment base | J19: Wave 5 | K19: New hub | L19: Wave 5: publish county/borough hub; city pages only where demand verified | M19: 289593 | N19: 236400 | O19: 127828 | P19: 121358 | Q19: 76556 | R19: =IF(AND(ISNUMBER(Q19),P19>0),Q19/P19,"") -> 0.6308278 | S19: 26208 | T19: =IF(AND(ISNUMBER(S19),Q19>0),S19/Q19,"") -> 0.34233764 | U19: =IF(AND(ISNUMBER(O19),O19>0),102328/O19,"") -> 0.80051319 | V19: 1972 | W19: 76242 | Z19: Annual homes sold not populated — source: Redfin Data Center county-level housing market download (homes sold, monthly); record period when filled; Investor purchase share not populated — Redfin/ATTOM investor data uses metro definitions; store only if the geography matches this row, else leave blank and note the metro figure in Rationale | AA19: US Census Bureau ACS via Census Reporter | AB19: ACS 2024 5-year (2020–2024) | AC19: https://censusreporter.org/profiles/05000US42043/ | AE19: https://www.clearedgehomebuyers.com/locations/pennsylvania/dauphin-county | AF19: /locations/pennsylvania | AG19: Harrisburg, Hershey
A20: PA | B20: South Central | C20: Cumberland County | D20: 42041 | E20: Cumberland County, PA | F20: page | H20: Tier 2 | I20: West-shore Harrisburg suburbs; higher values than Dauphin | J20: Wave 5 | K20: New hub | L20: Wave 5: publish county/borough hub; city pages only where demand verified | M20: 268323 | N20: 277600 | O20: 111278 | P20: 106427 | Q20: 75922 | R20: =IF(AND(ISNUMBER(Q20),P20>0),Q20/P20,"") -> 0.71337161 | S20: 24884 | T20: =IF(AND(ISNUMBER(S20),Q20>0),S20/Q20,"") -> 0.32775744 | U20: =IF(AND(ISNUMBER(O20),O20>0),92553/O20,"") -> 0.83172774 | V20: 1978 | W20: 87494 | Z20: Annual homes sold not populated — source: Redfin Data Center county-level housing market download (homes sold, monthly); record period when filled; Investor purchase share not populated — Redfin/ATTOM investor data uses metro definitions; store only if the geography matches this row, else leave blank and note the metro figure in Rationale | AA20: US Census Bureau ACS via Census Reporter | AB20: ACS 2024 5-year (2020–2024) | AC20: https://censusreporter.org/profiles/05000US42041/ | AE20: https://www.clearedgehomebuyers.com/locations/pennsylvania/cumberland-county | AF20: /locations/pennsylvania | AG20: Carlisle, Mechanicsburg, Camp Hill
A21: PA | B21: South Central | C21: Lebanon County | D21: 42075 | E21: Lebanon County, PA | F21: page | H21: Tier 3 | I21: Small market between Lancaster and Harrisburg; state-hub coverage | J21: Not scheduled | K21: CMS record only | L21: Record only — covered by state hub; no page scheduled | M21: 144186 | N21: 242000 | O21: 59921 | P21: 56712 | Q21: 40419 | R21: =IF(AND(ISNUMBER(Q21),P21>0),Q21/P21,"") -> 0.71270631 | S21: 14144 | T21: =IF(AND(ISNUMBER(S21),Q21>0),S21/Q21,"") -> 0.34993444 | U21: =IF(AND(ISNUMBER(O21),O21>0),51863/O21,"") -> 0.86552294 | V21: 1972 | W21: 78425 | Z21: Annual homes sold not populated — source: Redfin Data Center county-level housing market download (homes sold, monthly); record period when filled; Investor purchase share not populated — Redfin/ATTOM investor data uses metro definitions; store only if the geography matches this row, else leave blank and note the metro figure in Rationale | AA21: US Census Bureau ACS via Census Reporter | AB21: ACS 2024 5-year (2020–2024) | AC21: https://censusreporter.org/profiles/05000US42075/ | AF21: /locations/pennsylvania
A22: PA | B22: South Central | C22: Adams County | D22: 42001 | E22: Adams County, PA | F22: page | H22: Tier 3 | I22: Rural; state-hub coverage | J22: Not scheduled | K22: CMS record only | L22: Record only — covered by state hub; no page scheduled | M22: 106115 | N22: 268500 | O22: 43672 | P22: 40841 | Q22: 32214 | R22: =IF(AND(ISNUMBER(Q22),P22>0),Q22/P22,"") -> 0.78876619 | S22: 11766 | T22: =IF(AND(ISNUMBER(S22),Q22>0),S22/Q22,"") -> 0.36524492 | U22: =IF(AND(ISNUMBER(O22),O22>0),39116/O22,"") -> 0.89567686 | V22: 1980 | W22: 84092 | Z22: Annual homes sold not populated — source: Redfin Data Center county-level housing market download (homes sold, monthly); record period when filled; Investor purchase share not populated — Redfin/ATTOM investor data uses metro definitions; store only if the geography matches this row, else leave blank and note the metro figure in Rationale | AA22: US Census Bureau ACS via Census Reporter | AB22: ACS 2024 5-year (2020–2024) | AC22: https://censusreporter.org/profiles/05000US42001/ | AF22: /locations/pennsylvania
A23: PA | B23: South Central | C23: Franklin County | D23: 42055 | E23: Franklin County, PA | F23: page | H23: Tier 3 | I23: Rural; state-hub coverage | J23: Not scheduled | K23: CMS record only | L23: Record only — covered by state hub; no page scheduled | M23: 157379 | N23: 249800 | O23: 67157 | P23: 63510 | Q23: 46691 | R23: =IF(AND(ISNUMBER(Q23),P23>0),Q23/P23,"") -> 0.73517556 | S23: 15698 | T23: =IF(AND(ISNUMBER(S23),Q23>0),S23/Q23,"") -> 0.3362104 | U23: =IF(AND(ISNUMBER(O23),O23>0),58749/O23,"") -> 0.87480084 | V23: 1978 | W23: 77003 | Z23: Annual homes sold not populated — source: Redfin Data Center county-level housing market download (homes sold, monthly); record period when filled; Investor purchase share not populated — Redfin/ATTOM investor data uses metro definitions; store only if the geography matches this row, else leave blank and note the metro figure in Rationale | AA23: US Census Bureau ACS via Census Reporter | AB23: ACS 2024 5-year (2020–2024) | AC23: https://censusreporter.org/profiles/05000US42055/ | AF23: /locations/pennsylvania
A24: PA | B24: South Central | C24: Perry County | D24: 42099 | E24: Perry County, PA | F24: page | H24: Tier 3 | I24: Rural; state-hub coverage | J24: Not scheduled | K24: CMS record only | L24: Record only — covered by state hub; no page scheduled | M24: 46239 | N24: 236400 | O24: 20049 | P24: 18299 | Q24: 14974 | R24: =IF(AND(ISNUMBER(Q24),P24>0),Q24/P24,"") -> 0.81829608 | S24: 4878 | T24: =IF(AND(ISNUMBER(S24),Q24>0),S24/Q24,"") -> 0.32576466 | U24: =IF(AND(ISNUMBER(O24),O24>0),17744/O24,"") -> 0.88503167 | V24: 1976 | W24: 79444 | Z24: Annual homes sold not populated — source: Redfin Data Center county-level housing market download (homes sold, monthly); record period when filled; Investor purchase share not populated — Redfin/ATTOM investor data uses metro definitions; store only if the geography matches this row, else leave blank and note the metro figure in Rationale | AA24: US Census Bureau ACS via Census Reporter | AB24: ACS 2024 5-year (2020–2024) | AC24: https://censusreporter.org/profiles/05000US42099/ | AF24: /locations/pennsylvania
A25: PA | B25: NEPA | C25: Carbon County | D25: 42025 | E25: Carbon County, PA | F25: page | H25: Tier 3 | I25: Adjacent to Poconos; small; covered by Poconos region hub | J25: Not scheduled | K25: CMS record only | L25: Record only — covered by state hub; no page scheduled | M25: 65382 | N25: 211400 | O25: 34417 | P25: 27255 | Q25: 20824 | R25: =IF(AND(ISNUMBER(Q25),P25>0),Q25/P25,"") -> 0.76404329 | S25: 7864 | T25: =IF(AND(ISNUMBER(S25),Q25>0),S25/Q25,"") -> 0.37764118 | U25: =IF(AND(ISNUMBER(O25),O25>0),31361/O25,"") -> 0.91120667 | V25: 1972 | W25: 67554 | Z25: Annual homes sold not populated — source: Redfin Data Center county-level housing market download (homes sold, monthly); record period when filled; Investor purchase share not populated — Redfin/ATTOM investor data uses metro definitions; store only if the geography matches this row, else leave blank and note the metro figure in Rationale | AA25: US Census Bureau ACS via Census Reporter | AB25: ACS 2024 5-year (2020–2024) | AC25: https://censusreporter.org/profiles/05000US42025/ | AF25: /locations/poconos
A26: PA | B26: NEPA | C26: Pike County | D26: 42103 | E26: Pike County, PA | F26: page | H26: Tier 3 | I26: Adjacent to Poconos; second-home stock; covered by Poconos region hub | J26: Not scheduled | K26: CMS record only | L26: Record only — covered by state hub; no page scheduled | M26: 60621 | N26: 272600 | O26: 40177 | P26: 24262 | Q26: 21116 | R26: =IF(AND(ISNUMBER(Q26),P26>0),Q26/P26,"") -> 0.87033221 | S26: 7822 | T26: =IF(AND(ISNUMBER(S26),Q26>0),S26/Q26,"") -> 0.37043001 | U26: =IF(AND(ISNUMBER(O26),O26>0),37078/O26,"") -> 0.92286632 | V26: 1985 | W26: 81323 | Z26: Annual homes sold not populated — source: Redfin Data Center county-level housing market download (homes sold, monthly); record period when filled; Investor purchase share not populated — Redfin/ATTOM investor data uses metro definitions; store only if the geography matches this row, else leave blank and note the metro figure in Rationale | AA26: US Census Bureau ACS via Census Reporter | AB26: ACS 2024 5-year (2020–2024) | AC26: https://censusreporter.org/profiles/05000US42103/ | AF26: /locations/poconos
A27: PA | B27: NEPA | C27: Wyoming County | D27: 42131 | E27: Wyoming County, PA | F27: page | H27: Tier 3 | I27: Rural; covered by NEPA region hub | J27: Not scheduled | K27: CMS record only | L27: Record only — covered by state hub; no page scheduled | M27: 25967 | N27: 215400 | O27: 12896 | P27: 10912 | Q27: 8502 | R27: =IF(AND(ISNUMBER(Q27),P27>0),Q27/P27,"") -> 0.77914223 | S27: 3307 | T27: =IF(AND(ISNUMBER(S27),Q27>0),S27/Q27,"") -> 0.3889673 | U27: =IF(AND(ISNUMBER(O27),O27>0),11049/O27,"") -> 0.8567773 | V27: 1974 | W27: 72460 | Z27: Annual homes sold not populated — source: Redfin Data Center county-level housing market download (homes sold, monthly); record period when filled; Investor purchase share not populated — Redfin/ATTOM investor data uses metro definitions; store only if the geography matches this row, else leave blank and note the metro figure in Rationale | AA27: US Census Bureau ACS via Census Reporter | AB27: ACS 2024 5-year (2020–2024) | AC27: https://censusreporter.org/profiles/05000US42131/ | AF27: /locations/nepa
A28: PA | B28: NEPA | C28: Susquehanna County | D28: 42115 | E28: Susquehanna County, PA | F28: page | H28: Tier 3 | I28: Rural; covered by NEPA region hub | J28: Not scheduled | K28: CMS record only | L28: Record only — covered by state hub; no page scheduled | M28: 38219 | N28: 216400 | O28: 21348 | P28: 15517 | Q28: 12177 | R28: =IF(AND(ISNUMBER(Q28),P28>0),Q28/P28,"") -> 0.78475221 | S28: 5045 | T28: =IF(AND(ISNUMBER(S28),Q28>0),S28/Q28,"") -> 0.41430566 | U28: =IF(AND(ISNUMBER(O28),O28>0),18268/O28,"") -> 0.85572419 | V28: 1975 | W28: 68487 | Z28: Annual homes sold not populated — source: Redfin Data Center county-level housing market download (homes sold, monthly); record period when filled; Investor purchase share not populated — Redfin/ATTOM investor data uses metro definitions; store only if the geography matches this row, else leave blank and note the metro figure in Rationale | AA28: US Census Bureau ACS via Census Reporter | AB28: ACS 2024 5-year (2020–2024) | AC28: https://censusreporter.org/profiles/05000US42115/ | AF28: /locations/nepa
A29: PA | B29: NEPA | C29: Northumberland County | D29: 42097 | E29: Northumberland County, PA | F29: page | H29: Tier 3 | I29: Small; state-hub coverage | J29: Not scheduled | K29: CMS record only | L29: Record only — covered by state hub; no page scheduled | M29: 90560 | N29: 162400 | O29: 43395 | P29: 37886 | Q29: 28594 | R29: =IF(AND(ISNUMBER(Q29),P29>0),Q29/P29,"") -> 0.7547379 | S29: 10406 | T29: =IF(AND(ISNUMBER(S29),Q29>0),S29/Q29,"") -> 0.3639225 | U29: =IF(AND(ISNUMBER(O29),O29>0),38911/O29,"") -> 0.89667012 | V29: 1954 | W29: 60583 | Z29: Annual homes sold not populated — source: Redfin Data Center county-level housing market download (homes sold, monthly); record period when filled; Investor purchase share not populated — Redfin/ATTOM investor data uses metro definitions; store only if the geography matches this row, else leave blank and note the metro figure in Rationale | AA29: US Census Bureau ACS via Census Reporter | AB29: ACS 2024 5-year (2020–2024) | AC29: https://censusreporter.org/profiles/05000US42097/ | AF29: /locations/pennsylvania
A30: PA | B30: NEPA | C30: Bradford County | D30: 42015 | E30: Bradford County, PA | F30: page | H30: Tier 3 | I30: Rural; state-hub coverage | J30: Not scheduled | K30: CMS record only | L30: Record only — covered by state hub; no page scheduled | M30: 59858 | N30: 187500 | O30: 29486 | P30: 24610 | Q30: 17759 | R30: =IF(AND(ISNUMBER(Q30),P30>0),Q30/P30,"") -> 0.72161723 | S30: 6904 | T30: =IF(AND(ISNUMBER(S30),Q30>0),S30/Q30,"") -> 0.38876063 | U30: =IF(AND(ISNUMBER(O30),O30>0),23902/O30,"") -> 0.81062199 | V30: 1969 | W30: 63675 | Z30: Annual homes sold not populated — source: Redfin Data Center county-level housing market download (homes sold, monthly); record period when filled; Investor purchase share not populated — Redfin/ATTOM investor data uses metro definitions; store only if the geography matches this row, else leave blank and note the metro figure in Rationale | AA30: US Census Bureau ACS via Census Reporter | AB30: ACS 2024 5-year (2020–2024) | AC30: https://censusreporter.org/profiles/05000US42015/ | AF30: /locations/pennsylvania
A31: NJ | B31: North Jersey | C31: Bergen County | D31: 34003 | E31: Bergen County, NJ | F31: page | H31: Tier 1 | I31: Largest NJ county, very high values, dense aging single-family stock | J31: Wave 2 | K31: New hub | L31: Wave 2: publish county/borough hub; city pages only where demand verified | M31: 962316 | N31: 623000 | O31: 369613 | P31: 355127 | Q31: 232025 | R31: =IF(AND(ISNUMBER(Q31),P31>0),Q31/P31,"") -> 0.65335781 | S31: 76468 | T31: =IF(AND(ISNUMBER(S31),Q31>0),S31/Q31,"") -> 0.32956793 | U31: =IF(AND(ISNUMBER(O31),O31>0),285176/O31,"") -> 0.77155295 | V31: 1960 | W31: 124884 | Z31: Annual homes sold not populated — source: Redfin Data Center county-level housing market download (homes sold, monthly); record period when filled; Investor purchase share not populated — Redfin/ATTOM investor data uses metro definitions; store only if the geography matches this row, else leave blank and note the metro figure in Rationale | AA31: US Census Bureau ACS via Census Reporter | AB31: ACS 2024 5-year (2020–2024) | AC31: https://censusreporter.org/profiles/05000US34003/ | AE31: https://www.clearedgehomebuyers.com/locations/new-jersey/bergen-county | AF31: /locations/new-jersey | AG31: Hackensack, Teaneck, Fair Lawn, Paramus, Englewood
A32: NJ | B32: North Jersey | C32: Essex County | D32: 34013 | E32: Essex County, NJ | F32: page | H32: Tier 1 | I32: Meta campaign target; Newark investor volume plus high-value suburbs | J32: Wave 2 | K32: New hub | L32: Wave 2: publish county/borough hub; city pages only where demand verified | M32: 863002 | N32: 524100 | O32: 336962 | P32: 319788 | Q32: 143579 | R32: =IF(AND(ISNUMBER(Q32),P32>0),Q32/P32,"") -> 0.44898183 | S32: 43158 | T32: =IF(AND(ISNUMBER(S32),Q32>0),S32/Q32,"") -> 0.30058713 | U32: =IF(AND(ISNUMBER(O32),O32>0),231292/O32,"") -> 0.68640381 | V32: 1958 | W32: 80789 | Z32: Annual homes sold not populated — source: Redfin Data Center county-level housing market download (homes sold, monthly); record period when filled; Investor purchase share not populated — Redfin/ATTOM investor data uses metro definitions; store only if the geography matches this row, else leave blank and note the metro figure in Rationale | AA32: US Census Bureau ACS via Census Reporter | AB32: ACS 2024 5-year (2020–2024) | AC32: https://censusreporter.org/profiles/05000US34013/ | AE32: https://www.clearedgehomebuyers.com/locations/new-jersey/essex-county | AF32: /locations/new-jersey | AG32: Newark, East Orange, Irvington, Bloomfield, Montclair, West Orange
A33: NJ | B33: North Jersey | C33: Union County | D33: 34039 | E33: Union County, NJ | F33: page | H33: Tier 1 | I33: Meta campaign target; dense 1-4 family stock | J33: Wave 2 | K33: New hub | L33: Wave 2: publish county/borough hub; city pages only where demand verified | M33: 579290 | N33: 529200 | O33: 212385 | P33: 203277 | Q33: 116605 | R33: =IF(AND(ISNUMBER(Q33),P33>0),Q33/P33,"") -> 0.57362614 | S33: 34006 | T33: =IF(AND(ISNUMBER(S33),Q33>0),S33/Q33,"") -> 0.29163415 | U33: =IF(AND(ISNUMBER(O33),O33>0),168604/O33,"") -> 0.79386021 | V33: 1956 | W33: 103202 | Z33: Annual homes sold not populated — source: Redfin Data Center county-level housing market download (homes sold, monthly); record period when filled; Investor purchase share not populated — Redfin/ATTOM investor data uses metro definitions; store only if the geography matches this row, else leave blank and note the metro figure in Rationale | AA33: US Census Bureau ACS via Census Reporter | AB33: ACS 2024 5-year (2020–2024) | AC33: https://censusreporter.org/profiles/05000US34039/ | AE33: https://www.clearedgehomebuyers.com/locations/new-jersey/union-county | AF33: /locations/new-jersey | AG33: Elizabeth, Plainfield, Linden, Union, Rahway
A34: NJ | B34: North Jersey | C34: Passaic County | D34: 34031 | E34: Passaic County, NJ | F34: page | H34: Tier 1 | I34: Meta campaign target; Paterson investor volume, mid-to-high values | J34: Wave 2 | K34: New hub | L34: Wave 2: publish county/borough hub; city pages only where demand verified | M34: 521012 | N34: 459500 | O34: 185816 | P34: 178936 | Q34: 94970 | R34: =IF(AND(ISNUMBER(Q34),P34>0),Q34/P34,"") -> 0.53074842 | S34: 30437 | T34: =IF(AND(ISNUMBER(S34),Q34>0),S34/Q34,"") -> 0.32049068 | U34: =IF(AND(ISNUMBER(O34),O34>0),145999/O34,"") -> 0.78571813 | V34: 1956 | W34: 87522 | Z34: Annual homes sold not populated — source: Redfin Data Center county-level housing market download (homes sold, monthly); record period when filled; Investor purchase share not populated — Redfin/ATTOM investor data uses metro definitions; store only if the geography matches this row, else leave blank and note the metro figure in Rationale | AA34: US Census Bureau ACS via Census Reporter | AB34: ACS 2024 5-year (2020–2024) | AC34: https://censusreporter.org/profiles/05000US34031/ | AE34: https://www.clearedgehomebuyers.com/locations/new-jersey/passaic-county | AF34: /locations/new-jersey | AG34: Paterson, Clifton, Passaic, Wayne
A35: NJ | B35: North Jersey | C35: Hudson County | D35: 34017 | E35: Hudson County, NJ | F35: page | H35: Tier 1 | I35: Very dense, high values, heavy 2-4 family stock; condo-heavy waterfront | J35: Wave 2 | K35: New hub | L35: Wave 2: publish county/borough hub; city pages only where demand verified | M35: 718323 | N35: 539700 | O35: 320959 | P35: 299682 | Q35: 92074 | R35: =IF(AND(ISNUMBER(Q35),P35>0),Q35/P35,"") -> 0.30723901 | S35: 25121 | T35: =IF(AND(ISNUMBER(S35),Q35>0),S35/Q35,"") -> 0.27283489 | U35: =IF(AND(ISNUMBER(O35),O35>0),151134/O35,"") -> 0.47088257 | V35: 1966 | W35: 91795 | Z35: Annual homes sold not populated — source: Redfin Data Center county-level housing market download (homes sold, monthly); record period when filled; Investor purchase share not populated — Redfin/ATTOM investor data uses metro definitions; store only if the geography matches this row, else leave blank and note the metro figure in Rationale | AA35: US Census Bureau ACS via Census Reporter | AB35: ACS 2024 5-year (2020–2024) | AC35: https://censusreporter.org/profiles/05000US34017/ | AE35: https://www.clearedgehomebuyers.com/locations/new-jersey/hudson-county | AF35: /locations/new-jersey | AG35: Jersey City, Bayonne, Kearny, North Bergen, Union City
A36: NJ | B36: North Jersey | C36: Morris County | D36: 34027 | E36: Morris County, NJ | F36: page | H36: Tier 1 | I36: High values, older owner base, strong resale demand | J36: Wave 2 | K36: New hub | L36: Wave 2: publish county/borough hub; city pages only where demand verified | M36: 514528 | N36: 582500 | O36: 199506 | P36: 193245 | Q36: 143562 | R36: =IF(AND(ISNUMBER(Q36),P36>0),Q36/P36,"") -> 0.7429015 | S36: 43512 | T36: =IF(AND(ISNUMBER(S36),Q36>0),S36/Q36,"") -> 0.30308856 | U36: =IF(AND(ISNUMBER(O36),O36>0),160754/O36,"") -> 0.80576023 | V36: 1971 | W36: 137326 | Z36: Annual homes sold not populated — source: Redfin Data Center county-level housing market download (homes sold, monthly); record period when filled; Investor purchase share not populated — Redfin/ATTOM investor data uses metro definitions; store only if the geography matches this row, else leave blank and note the metro figure in Rationale | AA36: US Census Bureau ACS via Census Reporter | AB36: ACS 2024 5-year (2020–2024) | AC36: https://censusreporter.org/profiles/05000US34027/ | AE36: https://www.clearedgehomebuyers.com/locations/new-jersey/morris-county | AF36: /locations/new-jersey | AG36: Parsippany, Morristown, Dover, Randolph
A37: NJ | B37: Central Jersey | C37: Middlesex County | D37: 34023 | E37: Middlesex County, NJ | F37: page | H37: Tier 1 | I37: High volume, mid-to-high values, investor-active (New Brunswick) | J37: Wave 2 | K37: New hub | L37: Wave 2: publish county/borough hub; city pages only where demand verified | M37: 871290 | N37: 462900 | O37: 317979 | P37: 307782 | Q37: 195888 | R37: =IF(AND(ISNUMBER(Q37),P37>0),Q37/P37,"") -> 0.63645047 | S37: 61179 | T37: =IF(AND(ISNUMBER(S37),Q37>0),S37/Q37,"") -> 0.31231622 | U37: =IF(AND(ISNUMBER(O37),O37>0),238941/O37,"") -> 0.75143642 | V37: 1974 | W37: 111549 | Z37: Annual homes sold not populated — source: Redfin Data Center county-level housing market download (homes sold, monthly); record period when filled; Investor purchase share not populated — Redfin/ATTOM investor data uses metro definitions; store only if the geography matches this row, else leave blank and note the metro figure in Rationale | AA37: US Census Bureau ACS via Census Reporter | AB37: ACS 2024 5-year (2020–2024) | AC37: https://censusreporter.org/profiles/05000US34023/ | AE37: https://www.clearedgehomebuyers.com/locations/new-jersey/middlesex-county | AF37: /locations/new-jersey | AG37: Edison, Woodbridge, New Brunswick, Perth Amboy, Old Bridge
A38: NJ | B38: Central Jersey | C38: Monmouth County | D38: 34025 | E38: Monmouth County, NJ | F38: page | H38: Tier 1 | I38: High values, large housing base, shore and suburban mix | J38: Wave 2 | K38: New hub | L38: Wave 2: publish county/borough hub; city pages only where demand verified | M38: 645353 | N38: 606100 | O38: 270415 | P38: 251712 | Q38: 190173 | R38: =IF(AND(ISNUMBER(Q38),P38>0),Q38/P38,"") -> 0.75551821 | S38: 62262 | T38: =IF(AND(ISNUMBER(S38),Q38>0),S38/Q38,"") -> 0.32739663 | U38: =IF(AND(ISNUMBER(O38),O38>0),221517/O38,"") -> 0.81917423 | V38: 1975 | W38: 124845 | Z38: Annual homes sold not populated — source: Redfin Data Center county-level housing market download (homes sold, monthly); record period when filled; Investor purchase share not populated — Redfin/ATTOM investor data uses metro definitions; store only if the geography matches this row, else leave blank and note the metro figure in Rationale | AA38: US Census Bureau ACS via Census Reporter | AB38: ACS 2024 5-year (2020–2024) | AC38: https://censusreporter.org/profiles/05000US34025/ | AE38: https://www.clearedgehomebuyers.com/locations/new-jersey/monmouth-county | AF38: /locations/new-jersey | AG38: Freehold, Middletown, Long Branch, Neptune, Howell
A39: NJ | B39: Central Jersey | C39: Somerset County | D39: 34035 | E39: Somerset County, NJ | F39: page | H39: Tier 2 | I39: High values, lower volume | J39: Wave 5 | K39: New hub | L39: Wave 5: publish county/borough hub; city pages only where demand verified | M39: 349846 | N39: 552100 | O39: 133639 | P39: 130802 | Q39: 97187 | R39: =IF(AND(ISNUMBER(Q39),P39>0),Q39/P39,"") -> 0.74300852 | S39: 27905 | T39: =IF(AND(ISNUMBER(S39),Q39>0),S39/Q39,"") -> 0.28712688 | U39: =IF(AND(ISNUMBER(O39),O39>0),109702/O39,"") -> 0.82088313 | V39: 1982 | W39: 140374 | Z39: Annual homes sold not populated — source: Redfin Data Center county-level housing market download (homes sold, monthly); record period when filled; Investor purchase share not populated — Redfin/ATTOM investor data uses metro definitions; store only if the geography matches this row, else leave blank and note the metro figure in Rationale | AA39: US Census Bureau ACS via Census Reporter | AB39: ACS 2024 5-year (2020–2024) | AC39: https://censusreporter.org/profiles/05000US34035/ | AE39: https://www.clearedgehomebuyers.com/locations/new-jersey/somerset-county | AF39: /locations/new-jersey | AG39: Franklin, Bridgewater, Somerville
A40: NJ | B40: Central Jersey | C40: Mercer County | D40: 34021 | E40: Mercer County, NJ | F40: page | H40: Tier 2 | I40: Trenton investor volume plus high-value suburbs | J40: Wave 5 | K40: New hub | L40: Wave 5: publish county/borough hub; city pages only where demand verified | M40: 385864 | N40: 377700 | O40: 151138 | P40: 144114 | Q40: 89569 | R40: =IF(AND(ISNUMBER(Q40),P40>0),Q40/P40,"") -> 0.62151491 | S40: 28133 | T40: =IF(AND(ISNUMBER(S40),Q40>0),S40/Q40,"") -> 0.31409305 | U40: =IF(AND(ISNUMBER(O40),O40>0),115278/O40,"") -> 0.7627334 | V40: 1969 | W40: 100645 | Z40: Annual homes sold not populated — source: Redfin Data Center county-level housing market download (homes sold, monthly); record period when filled; Investor purchase share not populated — Redfin/ATTOM investor data uses metro definitions; store only if the geography matches this row, else leave blank and note the metro figure in Rationale | AA40: US Census Bureau ACS via Census Reporter | AB40: ACS 2024 5-year (2020–2024) | AC40: https://censusreporter.org/profiles/05000US34021/ | AE40: https://www.clearedgehomebuyers.com/locations/new-jersey/mercer-county | AF40: /locations/new-jersey | AG40: Trenton, Hamilton, Ewing
A41: NJ | B41: Shore | C41: Ocean County | D41: 34029 | E41: Ocean County, NJ | F41: page | H41: Tier 2 | I41: Very large housing base, mid values, heavy 55+ ownership | J41: Wave 5 | K41: New hub | L41: Wave 5: publish county/borough hub; city pages only where demand verified | M41: 654362 | N41: 398400 | O41: 296357 | P41: 243843 | Q41: 196874 | R41: =IF(AND(ISNUMBER(Q41),P41>0),Q41/P41,"") -> 0.80738016 | S41: 85187 | T41: =IF(AND(ISNUMBER(S41),Q41>0),S41/Q41,"") -> 0.43269807 | U41: =IF(AND(ISNUMBER(O41),O41>0),265773/O41,"") -> 0.89680014 | V41: 1981 | W41: 89863 | Z41: Annual homes sold not populated — source: Redfin Data Center county-level housing market download (homes sold, monthly); record period when filled; Investor purchase share not populated — Redfin/ATTOM investor data uses metro definitions; store only if the geography matches this row, else leave blank and note the metro figure in Rationale | AA41: US Census Bureau ACS via Census Reporter | AB41: ACS 2024 5-year (2020–2024) | AC41: https://censusreporter.org/profiles/05000US34029/ | AE41: https://www.clearedgehomebuyers.com/locations/new-jersey/ocean-county | AF41: /locations/new-jersey | AG41: Toms River, Brick, Lakewood, Jackson
A42: NJ | B42: South Jersey | C42: Burlington County | D42: 34005 | E42: Burlington County, NJ | F42: page | H42: Tier 2 | I42: Mid values, Philly-adjacent, steady volume | J42: Wave 5 | K42: New hub | L42: Wave 5: publish county/borough hub; city pages only where demand verified | M42: 467805 | N42: 354000 | O42: 186315 | P42: 177222 | Q42: 134924 | R42: =IF(AND(ISNUMBER(Q42),P42>0),Q42/P42,"") -> 0.7613276 | S42: 43733 | T42: =IF(AND(ISNUMBER(S42),Q42>0),S42/Q42,"") -> 0.32413062 | U42: =IF(AND(ISNUMBER(O42),O42>0),156508/O42,"") -> 0.84001825 | V42: 1977 | W42: 108111 | Z42: Annual homes sold not populated — source: Redfin Data Center county-level housing market download (homes sold, monthly); record period when filled; Investor purchase share not populated — Redfin/ATTOM investor data uses metro definitions; store only if the geography matches this row, else leave blank and note the metro figure in Rationale | AA42: US Census Bureau ACS via Census Reporter | AB42: ACS 2024 5-year (2020–2024) | AC42: https://censusreporter.org/profiles/05000US34005/ | AE42: https://www.clearedgehomebuyers.com/locations/new-jersey/burlington-county | AF42: /locations/new-jersey | AG42: Mount Laurel, Willingboro, Burlington
A43: NJ | B43: South Jersey | C43: Camden County | D43: 34007 | E43: Camden County, NJ | F43: page | H43: Tier 2 | I43: Mid-to-low values, high investor activity | J43: Wave 5 | K43: New hub | L43: Wave 5: publish county/borough hub; city pages only where demand verified | M43: 527257 | N43: 287100 | O43: 213774 | P43: 202540 | Q43: 131032 | R43: =IF(AND(ISNUMBER(Q43),P43>0),Q43/P43,"") -> 0.64694381 | S43: 40290 | T43: =IF(AND(ISNUMBER(S43),Q43>0),S43/Q43,"") -> 0.30748214 | U43: =IF(AND(ISNUMBER(O43),O43>0),169374/O43,"") -> 0.79230402 | V43: 1967 | W43: 88755 | Z43: Annual homes sold not populated — source: Redfin Data Center county-level housing market download (homes sold, monthly); record period when filled; Investor purchase share not populated — Redfin/ATTOM investor data uses metro definitions; store only if the geography matches this row, else leave blank and note the metro figure in Rationale | AA43: US Census Bureau ACS via Census Reporter | AB43: ACS 2024 5-year (2020–2024) | AC43: https://censusreporter.org/profiles/05000US34007/ | AE43: https://www.clearedgehomebuyers.com/locations/new-jersey/camden-county | AF43: /locations/new-jersey | AG43: Camden, Cherry Hill, Pennsauken
A44: NJ | B44: South Jersey | C44: Gloucester County | D44: 34015 | E44: Gloucester County, NJ | F44: page | H44: Tier 2 | I44: Mid values, Philly-adjacent | J44: Wave 5 | K44: New hub | L44: Wave 5: publish county/borough hub; city pages only where demand verified | M44: 306954 | N44: 310400 | O44: 117915 | P44: 112545 | Q44: 90175 | R44: =IF(AND(ISNUMBER(Q44),P44>0),Q44/P44,"") -> 0.80123506 | S44: 26843 | T44: =IF(AND(ISNUMBER(S44),Q44>0),S44/Q44,"") -> 0.29767674 | U44: =IF(AND(ISNUMBER(O44),O44>0),102428/O44,"") -> 0.86865963 | V44: 1980 | W44: 105115 | Z44: Annual homes sold not populated — source: Redfin Data Center county-level housing market download (homes sold, monthly); record period when filled; Investor purchase share not populated — Redfin/ATTOM investor data uses metro definitions; store only if the geography matches this row, else leave blank and note the metro figure in Rationale | AA44: US Census Bureau ACS via Census Reporter | AB44: ACS 2024 5-year (2020–2024) | AC44: https://censusreporter.org/profiles/05000US34015/ | AE44: https://www.clearedgehomebuyers.com/locations/new-jersey/gloucester-county | AF44: /locations/new-jersey | AG44: Glassboro, Deptford, Washington Twp
A45: NJ | B45: North Jersey | C45: Hunterdon County | D45: 34019 | E45: Hunterdon County, NJ | F45: page | H45: Tier 2 | I45: High values, low volume, rural-suburban | J45: Wave 5 | K45: New hub | L45: Wave 5: publish county/borough hub; city pages only where demand verified | M45: 130160 | N45: 517200 | O45: 52115 | P45: 50860 | Q45: 43302 | R45: =IF(AND(ISNUMBER(Q45),P45>0),Q45/P45,"") -> 0.85139599 | S45: 13850 | T45: =IF(AND(ISNUMBER(S45),Q45>0),S45/Q45,"") -> 0.31984666 | U45: =IF(AND(ISNUMBER(O45),O45>0),47954/O45,"") -> 0.92015734 | V45: 1979 | W45: 141715 | Z45: Annual homes sold not populated — source: Redfin Data Center county-level housing market download (homes sold, monthly); record period when filled; Investor purchase share not populated — Redfin/ATTOM investor data uses metro definitions; store only if the geography matches this row, else leave blank and note the metro figure in Rationale | AA45: US Census Bureau ACS via Census Reporter | AB45: ACS 2024 5-year (2020–2024) | AC45: https://censusreporter.org/profiles/05000US34019/ | AE45: https://www.clearedgehomebuyers.com/locations/new-jersey/hunterdon-county | AF45: /locations/new-jersey | AG45: Flemington
A46: NJ | B46: North Jersey | C46: Sussex County | D46: 34037 | E46: Sussex County, NJ | F46: page | H46: Tier 3 | I46: Rural; state-hub coverage | J46: Not scheduled | K46: CMS record only | L46: Record only — covered by state hub; no page scheduled | M46: 145807 | N46: 369400 | O46: 62865 | P46: 57767 | Q46: 48366 | R46: =IF(AND(ISNUMBER(Q46),P46>0),Q46/P46,"") -> 0.83726003 | S46: 14029 | T46: =IF(AND(ISNUMBER(S46),Q46>0),S46/Q46,"") -> 0.29005913 | U46: =IF(AND(ISNUMBER(O46),O46>0),56504/O46,"") -> 0.89881492 | V46: 1973 | W46: 116186 | Z46: Annual homes sold not populated — source: Redfin Data Center county-level housing market download (homes sold, monthly); record period when filled; Investor purchase share not populated — Redfin/ATTOM investor data uses metro definitions; store only if the geography matches this row, else leave blank and note the metro figure in Rationale | AA46: US Census Bureau ACS via Census Reporter | AB46: ACS 2024 5-year (2020–2024) | AC46: https://censusreporter.org/profiles/05000US34037/ | AF46: /locations/new-jersey
A47: NJ | B47: North Jersey | C47: Warren County | D47: 34041 | E47: Warren County, NJ | F47: page | H47: Tier 3 | I47: Rural; state-hub coverage | J47: Not scheduled | K47: CMS record only | L47: Record only — covered by state hub; no page scheduled | M47: 110849 | N47: 346500 | O47: 46789 | P47: 45391 | Q47: 34072 | R47: =IF(AND(ISNUMBER(Q47),P47>0),Q47/P47,"") -> 0.75063339 | S47: 10777 | T47: =IF(AND(ISNUMBER(S47),Q47>0),S47/Q47,"") -> 0.31630077 | U47: =IF(AND(ISNUMBER(O47),O47>0),40845/O47,"") -> 0.87296159 | V47: 1972 | W47: 100869 | Z47: Annual homes sold not populated — source: Redfin Data Center county-level housing market download (homes sold, monthly); record period when filled; Investor purchase share not populated — Redfin/ATTOM investor data uses metro definitions; store only if the geography matches this row, else leave blank and note the metro figure in Rationale | AA47: US Census Bureau ACS via Census Reporter | AB47: ACS 2024 5-year (2020–2024) | AC47: https://censusreporter.org/profiles/05000US34041/ | AF47: /locations/new-jersey
A48: NJ | B48: South Jersey | C48: Atlantic County | D48: 34001 | E48: Atlantic County, NJ | F48: page | H48: Tier 3 | I48: Shore; state-hub coverage | J48: Not scheduled | K48: CMS record only | L48: Record only — covered by state hub; no page scheduled | M48: 276270 | N48: 295000 | O48: 132199 | P48: 109557 | Q48: 75281 | R48: =IF(AND(ISNUMBER(Q48),P48>0),Q48/P48,"") -> 0.68714003 | S48: 27467 | T48: =IF(AND(ISNUMBER(S48),Q48>0),S48/Q48,"") -> 0.36485966 | U48: =IF(AND(ISNUMBER(O48),O48>0),100808/O48,"") -> 0.76254737 | V48: 1978 | W48: 78050 | Z48: Annual homes sold not populated — source: Redfin Data Center county-level housing market download (homes sold, monthly); record period when filled; Investor purchase share not populated — Redfin/ATTOM investor data uses metro definitions; store only if the geography matches this row, else leave blank and note the metro figure in Rationale | AA48: US Census Bureau ACS via Census Reporter | AB48: ACS 2024 5-year (2020–2024) | AC48: https://censusreporter.org/profiles/05000US34001/ | AF48: /locations/new-jersey
A49: NJ | B49: South Jersey | C49: Cape May County | D49: 34009 | E49: Cape May County, NJ | F49: page | H49: Tier 3 | I49: Seasonal shore; state-hub coverage | J49: Not scheduled | K49: CMS record only | L49: Record only — covered by state hub; no page scheduled | M49: 94941 | N49: 434600 | O49: 99599 | P49: 44884 | Q49: 36053 | R49: =IF(AND(ISNUMBER(Q49),P49>0),Q49/P49,"") -> 0.80324837 | S49: 15876 | T49: =IF(AND(ISNUMBER(S49),Q49>0),S49/Q49,"") -> 0.4403517 | U49: =IF(AND(ISNUMBER(O49),O49>0),87600/O49,"") -> 0.8795269 | V49: 1981 | W49: 91128 | Z49: Annual homes sold not populated — source: Redfin Data Center county-level housing market download (homes sold, monthly); record period when filled; Investor purchase share not populated — Redfin/ATTOM investor data uses metro definitions; store only if the geography matches this row, else leave blank and note the metro figure in Rationale | AA49: US Census Bureau ACS via Census Reporter | AB49: ACS 2024 5-year (2020–2024) | AC49: https://censusreporter.org/profiles/05000US34009/ | AF49: /locations/new-jersey
A50: NJ | B50: South Jersey | C50: Cumberland County | D50: 34011 | E50: Cumberland County, NJ | F50: page | H50: Tier 3 | I50: Low values; state-hub coverage | J50: Not scheduled | K50: CMS record only | L50: Record only — covered by state hub; no page scheduled | M50: 153305 | N50: 221400 | O50: 57282 | P50: 53781 | Q50: 35782 | R50: =IF(AND(ISNUMBER(Q50),P50>0),Q50/P50,"") -> 0.6653279 | S50: 11464 | T50: =IF(AND(ISNUMBER(S50),Q50>0),S50/Q50,"") -> 0.32038455 | U50: =IF(AND(ISNUMBER(O50),O50>0),47564/O50,"") -> 0.8303481 | V50: 1969 | W50: 67436 | Z50: Annual homes sold not populated — source: Redfin Data Center county-level housing market download (homes sold, monthly); record period when filled; Investor purchase share not populated — Redfin/ATTOM investor data uses metro definitions; store only if the geography matches this row, else leave blank and note the metro figure in Rationale | AA50: US Census Bureau ACS via Census Reporter | AB50: ACS 2024 5-year (2020–2024) | AC50: https://censusreporter.org/profiles/05000US34011/ | AF50: /locations/new-jersey
A51: NJ | B51: South Jersey | C51: Salem County | D51: 34033 | E51: Salem County, NJ | F51: page | H51: Tier 3 | I51: Rural, low values; state-hub coverage | J51: Not scheduled | K51: CMS record only | L51: Record only — covered by state hub; no page scheduled | M51: 65275 | N51: 239500 | O51: 27732 | P51: 24846 | Q51: 17635 | R51: =IF(AND(ISNUMBER(Q51),P51>0),Q51/P51,"") -> 0.7097722 | S51: 6336 | T51: =IF(AND(ISNUMBER(S51),Q51>0),S51/Q51,"") -> 0.35928551 | U51: =IF(AND(ISNUMBER(O51),O51>0),24203/O51,"") -> 0.87274629 | V51: 1962 | W51: 79960 | Z51: Annual homes sold not populated — source: Redfin Data Center county-level housing market download (homes sold, monthly); record period when filled; Investor purchase share not populated — Redfin/ATTOM investor data uses metro definitions; store only if the geography matches this row, else leave blank and note the metro figure in Rationale | AA51: US Census Bureau ACS via Census Reporter | AB51: ACS 2024 5-year (2020–2024) | AC51: https://censusreporter.org/profiles/05000US34033/ | AF51: /locations/new-jersey
A52: NY | B52: New York City | C52: Queens | D52: 36081 | E52: Queens County, NY | F52: page | H52: Tier 1 | I52: Home turf; largest 1-4 family stock in NYC; heavy inheritance volume | J52: Wave 3 | K52: New hub | L52: Wave 3: publish county/borough hub; city pages only where demand verified | M52: 2323052 | N52: 723800 | O52: 910206 | P52: 841003 | Q52: 377295 | R52: =IF(AND(ISNUMBER(Q52),P52>0),Q52/P52,"") -> 0.44862503 | S52: 141313 | T52: =IF(AND(ISNUMBER(S52),Q52>0),S52/Q52,"") -> 0.37454247 | U52: =IF(AND(ISNUMBER(O52),O52>0),529416/O52,"") -> 0.58164416 | V52: 1953 | W52: 86136 | Z52: Annual homes sold not populated — source: Redfin Data Center county-level housing market download (homes sold, monthly); record period when filled; Investor purchase share not populated — Redfin/ATTOM investor data uses metro definitions; store only if the geography matches this row, else leave blank and note the metro figure in Rationale | AA52: US Census Bureau ACS via Census Reporter | AB52: ACS 2024 5-year (2020–2024) | AC52: https://censusreporter.org/profiles/05000US36081/ | AE52: https://www.clearedgehomebuyers.com/locations/new-york/queens | AF52: /locations/new-york/new-york-city | AG52: Flushing, Jamaica, Ridgewood, Bayside, Rego Park (neighborhood pages, selective)
A53: NY | B53: New York City | C53: Brooklyn (Kings) | D53: 36047 | E53: Kings County, NY | F53: page | H53: Tier 1 | I53: Very high values, large 2-4 family stock, aging owners | J53: Wave 3 | K53: New hub | L53: Wave 3: publish county/borough hub; city pages only where demand verified | M53: 2631580 | N53: 905000 | O53: 1100772 | P53: 1009927 | Q53: 297916 | R53: =IF(AND(ISNUMBER(Q53),P53>0),Q53/P53,"") -> 0.29498766 | S53: 104837 | T53: =IF(AND(ISNUMBER(S53),Q53>0),S53/Q53,"") -> 0.35190121 | U53: =IF(AND(ISNUMBER(O53),O53>0),492518/O53,"") -> 0.44742962 | V53: 1944 | W53: 80263 | Z53: Annual homes sold not populated — source: Redfin Data Center county-level housing market download (homes sold, monthly); record period when filled; Investor purchase share not populated — Redfin/ATTOM investor data uses metro definitions; store only if the geography matches this row, else leave blank and note the metro figure in Rationale | AA53: US Census Bureau ACS via Census Reporter | AB53: ACS 2024 5-year (2020–2024) | AC53: https://censusreporter.org/profiles/05000US36047/ | AE53: https://www.clearedgehomebuyers.com/locations/new-york/brooklyn | AF53: /locations/new-york/new-york-city | AG53: Canarsie, Bushwick, East Flatbush, Bensonhurst (selective)
A54: NY | B54: New York City | C54: Bronx | D54: 36005 | E54: Bronx County, NY | F54: page | H54: Tier 1 | I54: Mid-to-high values, 1-4 family stock in east/north Bronx | J54: Wave 3 | K54: New hub | L54: Wave 3: publish county/borough hub; city pages only where demand verified | M54: 1404779 | N54: 529500 | O54: 559415 | P54: 534100 | Q54: 107175 | R54: =IF(AND(ISNUMBER(Q54),P54>0),Q54/P54,"") -> 0.20066467 | S54: 37786 | T54: =IF(AND(ISNUMBER(S54),Q54>0),S54/Q54,"") -> 0.35256356 | U54: =IF(AND(ISNUMBER(O54),O54>0),157733/O54,"") -> 0.28196062 | V54: 1955 | W54: 48676 | Z54: Annual homes sold not populated — source: Redfin Data Center county-level housing market download (homes sold, monthly); record period when filled; Investor purchase share not populated — Redfin/ATTOM investor data uses metro definitions; store only if the geography matches this row, else leave blank and note the metro figure in Rationale | AA54: US Census Bureau ACS via Census Reporter | AB54: ACS 2024 5-year (2020–2024) | AC54: https://censusreporter.org/profiles/05000US36005/ | AE54: https://www.clearedgehomebuyers.com/locations/new-york/bronx | AF54: /locations/new-york/new-york-city | AG54: Throggs Neck, Wakefield, Soundview (selective)
A55: NY | B55: New York City | C55: Staten Island (Richmond) | D55: 36085 | E55: Richmond County, NY | F55: page | H55: Tier 1 | I55: Most single-family of the boroughs; suburban-style inherited homes | J55: Wave 3 | K55: New hub | L55: Wave 3: publish county/borough hub; city pages only where demand verified | M55: 494956 | N55: 675500 | O55: 184621 | P55: 170777 | Q55: 115688 | R55: =IF(AND(ISNUMBER(Q55),P55>0),Q55/P55,"") -> 0.67742143 | S55: 36096 | T55: =IF(AND(ISNUMBER(S55),Q55>0),S55/Q55,"") -> 0.31201162 | U55: =IF(AND(ISNUMBER(O55),O55>0),159517/O55,"") -> 0.86402414 | V55: 1974 | W55: 98333 | Z55: Annual homes sold not populated — source: Redfin Data Center county-level housing market download (homes sold, monthly); record period when filled; Investor purchase share not populated — Redfin/ATTOM investor data uses metro definitions; store only if the geography matches this row, else leave blank and note the metro figure in Rationale | AA55: US Census Bureau ACS via Census Reporter | AB55: ACS 2024 5-year (2020–2024) | AC55: https://censusreporter.org/profiles/05000US36085/ | AE55: https://www.clearedgehomebuyers.com/locations/new-york/staten-island | AF55: /locations/new-york/new-york-city | AG55: St. George, Tottenville, New Dorp (selective)
A56: NY | B56: New York City | C56: Manhattan (New York) | D56: 36061 | E56: New York County, NY | F56: page | H56: Tier 2 | I56: Co-op/condo dominant; few 1-4 family homes; hub only | J56: Wave 5 | K56: New hub | L56: Wave 5: publish county/borough hub; city pages only where demand verified | M56: 1629477 | N56: 1090500 | O56: 923472 | P56: 778281 | Q56: 194982 | R56: =IF(AND(ISNUMBER(Q56),P56>0),Q56/P56,"") -> 0.25052905 | S56: 70646 | T56: =IF(AND(ISNUMBER(S56),Q56>0),S56/Q56,"") -> 0.36232062 | U56: =IF(AND(ISNUMBER(O56),O56>0),43366/O56,"") -> 0.046959735 | V56: 1951 | W56: 103931 | Z56: Annual homes sold not populated — source: Redfin Data Center county-level housing market download (homes sold, monthly); record period when filled; Investor purchase share not populated — Redfin/ATTOM investor data uses metro definitions; store only if the geography matches this row, else leave blank and note the metro figure in Rationale | AA56: US Census Bureau ACS via Census Reporter | AB56: ACS 2024 5-year (2020–2024) | AC56: https://censusreporter.org/profiles/05000US36061/ | AE56: https://www.clearedgehomebuyers.com/locations/new-york/manhattan | AF56: /locations/new-york/new-york-city | AG56: Harlem, Washington Heights (selective, townhouse stock)
A57: NY | B57: Long Island | C57: Nassau County | D57: 36059 | E57: Nassau County, NY | F57: page | H57: Tier 1 | I57: Very high values, large aging single-family base, LIRR employer proximity | J57: Wave 3 | K57: New hub | L57: Wave 3: publish county/borough hub; city pages only where demand verified | M57: 1389591 | N57: 684700 | O57: 479044 | P57: 458166 | Q57: 375466 | R57: =IF(AND(ISNUMBER(Q57),P57>0),Q57/P57,"") -> 0.81949774 | S57: 125819 | T57: =IF(AND(ISNUMBER(S57),Q57>0),S57/Q57,"") -> 0.33510091 | U57: =IF(AND(ISNUMBER(O57),O57>0),415697/O57,"") -> 0.86776371 | V57: 1955 | W57: 146202 | Z57: Annual homes sold not populated — source: Redfin Data Center county-level housing market download (homes sold, monthly); record period when filled; Investor purchase share not populated — Redfin/ATTOM investor data uses metro definitions; store only if the geography matches this row, else leave blank and note the metro figure in Rationale | AA57: US Census Bureau ACS via Census Reporter | AB57: ACS 2024 5-year (2020–2024) | AC57: https://censusreporter.org/profiles/05000US36059/ | AE57: https://www.clearedgehomebuyers.com/locations/new-york/nassau-county | AF57: /locations/new-york/long-island | AG57: Hempstead, Freeport, Levittown, Valley Stream, Long Beach
A58: NY | B58: Long Island | C58: Suffolk County | D58: 36103 | E58: Suffolk County, NY | F58: page | H58: Tier 1 | I58: Largest LI housing base, high values, wide spread variance west to east | J58: Wave 3 | K58: New hub | L58: Wave 3: publish county/borough hub; city pages only where demand verified | M58: 1530146 | N58: 578400 | O58: 580772 | P58: 512565 | Q58: 421146 | R58: =IF(AND(ISNUMBER(Q58),P58>0),Q58/P58,"") -> 0.82164408 | S58: 137065 | T58: =IF(AND(ISNUMBER(S58),Q58>0),S58/Q58,"") -> 0.3254572 | U58: =IF(AND(ISNUMBER(O58),O58>0),524675/O58,"") -> 0.9034096 | V58: 1970 | W58: 130686 | Z58: Annual homes sold not populated — source: Redfin Data Center county-level housing market download (homes sold, monthly); record period when filled; Investor purchase share not populated — Redfin/ATTOM investor data uses metro definitions; store only if the geography matches this row, else leave blank and note the metro figure in Rationale | AA58: US Census Bureau ACS via Census Reporter | AB58: ACS 2024 5-year (2020–2024) | AC58: https://censusreporter.org/profiles/05000US36103/ | AE58: https://www.clearedgehomebuyers.com/locations/new-york/suffolk-county | AF58: /locations/new-york/long-island | AG58: Brentwood, Bay Shore, Huntington Station, Patchogue, Riverhead
A59: NY | B59: Westchester & Hudson Valley | C59: Westchester County | D59: 36119 | E59: Westchester County, NY | F59: page | H59: Tier 1 | I59: ~1M residents, very high values; town selection matters | J59: Wave 3 | K59: New hub | L59: Wave 3: publish county/borough hub; city pages only where demand verified | M59: 999677 | N59: 663200 | O59: 394358 | P59: 372883 | Q59: 230602 | R59: =IF(AND(ISNUMBER(Q59),P59>0),Q59/P59,"") -> 0.61842991 | S59: 78921 | T59: =IF(AND(ISNUMBER(S59),Q59>0),S59/Q59,"") -> 0.34223901 | U59: =IF(AND(ISNUMBER(O59),O59>0),254215/O59,"") -> 0.64463001 | V59: 1959 | W59: 118976 | Z59: Annual homes sold not populated — source: Redfin Data Center county-level housing market download (homes sold, monthly); record period when filled; Investor purchase share not populated — Redfin/ATTOM investor data uses metro definitions; store only if the geography matches this row, else leave blank and note the metro figure in Rationale | AA59: US Census Bureau ACS via Census Reporter | AB59: ACS 2024 5-year (2020–2024) | AC59: https://censusreporter.org/profiles/05000US36119/ | AE59: https://www.clearedgehomebuyers.com/locations/new-york/westchester-county | AF59: /locations/new-york | AG59: Yonkers, Mount Vernon, New Rochelle, White Plains, Peekskill
A60: NY | B60: Westchester & Hudson Valley | C60: Rockland County | D60: 36087 | E60: Rockland County, NY | F60: page | H60: Tier 1 | I60: High values, dense suburban stock | J60: Wave 3 | K60: New hub | L60: Wave 3: publish county/borough hub; city pages only where demand verified | M60: 341883 | N60: 596900 | O60: 108945 | P60: 103879 | Q60: 70564 | R60: =IF(AND(ISNUMBER(Q60),P60>0),Q60/P60,"") -> 0.67929033 | S60: 24321 | T60: =IF(AND(ISNUMBER(S60),Q60>0),S60/Q60,"") -> 0.34466584 | U60: =IF(AND(ISNUMBER(O60),O60>0),86320/O60,"") -> 0.7923264 | V60: 1971 | W60: 109959 | Z60: Annual homes sold not populated — source: Redfin Data Center county-level housing market download (homes sold, monthly); record period when filled; Investor purchase share not populated — Redfin/ATTOM investor data uses metro definitions; store only if the geography matches this row, else leave blank and note the metro figure in Rationale | AA60: US Census Bureau ACS via Census Reporter | AB60: ACS 2024 5-year (2020–2024) | AC60: https://censusreporter.org/profiles/05000US36087/ | AE60: https://www.clearedgehomebuyers.com/locations/new-york/rockland-county | AF60: /locations/new-york | AG60: Spring Valley, Nanuet, Suffern, Haverstraw
A61: NY | B61: Westchester & Hudson Valley | C61: Orange County | D61: 36071 | E61: Orange County, NY | F61: page | H61: Tier 2 | I61: Mid values, growing, PA-like economics | J61: Wave 5 | K61: New hub | L61: Wave 5: publish county/borough hub; city pages only where demand verified | M61: 406616 | N61: 387900 | O61: 149699 | P61: 138608 | Q61: 94002 | R61: =IF(AND(ISNUMBER(Q61),P61>0),Q61/P61,"") -> 0.67818596 | S61: 26746 | T61: =IF(AND(ISNUMBER(S61),Q61>0),S61/Q61,"") -> 0.28452586 | U61: =IF(AND(ISNUMBER(O61),O61>0),119865/O61,"") -> 0.80070675 | V61: 1975 | W61: 97178 | Z61: Annual homes sold not populated — source: Redfin Data Center county-level housing market download (homes sold, monthly); record period when filled; Investor purchase share not populated — Redfin/ATTOM investor data uses metro definitions; store only if the geography matches this row, else leave blank and note the metro figure in Rationale | AA61: US Census Bureau ACS via Census Reporter | AB61: ACS 2024 5-year (2020–2024) | AC61: https://censusreporter.org/profiles/05000US36071/ | AE61: https://www.clearedgehomebuyers.com/locations/new-york/orange-county | AF61: /locations/new-york | AG61: Newburgh, Middletown, Monroe
A62: NY | B62: Westchester & Hudson Valley | C62: Putnam County | D62: 36079 | E62: Putnam County, NY | F62: page | H62: Tier 2 | I62: High values, low volume | J62: Wave 5 | K62: New hub | L62: Wave 5: publish county/borough hub; city pages only where demand verified | M62: 98107 | N62: 471300 | O62: 38450 | P62: 35545 | Q62: 29778 | R62: =IF(AND(ISNUMBER(Q62),P62>0),Q62/P62,"") -> 0.83775496 | S62: 9396 | T62: =IF(AND(ISNUMBER(S62),Q62>0),S62/Q62,"") -> 0.31553496 | U62: =IF(AND(ISNUMBER(O62),O62>0),35680/O62,"") -> 0.92795839 | V62: 1968 | W62: 126257 | Z62: Annual homes sold not populated — source: Redfin Data Center county-level housing market download (homes sold, monthly); record period when filled; Investor purchase share not populated — Redfin/ATTOM investor data uses metro definitions; store only if the geography matches this row, else leave blank and note the metro figure in Rationale | AA62: US Census Bureau ACS via Census Reporter | AB62: ACS 2024 5-year (2020–2024) | AC62: https://censusreporter.org/profiles/05000US36079/ | AE62: https://www.clearedgehomebuyers.com/locations/new-york/putnam-county | AF62: /locations/new-york | AG62: Carmel, Brewster
A63: NY | B63: Westchester & Hudson Valley | C63: Dutchess County | D63: 36027 | E63: Dutchess County, NY | F63: page | H63: Tier 2 | I63: Mid values, Poughkeepsie investor activity | J63: Wave 5 | K63: New hub | L63: Wave 5: publish county/borough hub; city pages only where demand verified | M63: 298220 | N63: 400600 | O63: 123169 | P63: 116275 | Q63: 80447 | R63: =IF(AND(ISNUMBER(Q63),P63>0),Q63/P63,"") -> 0.69186842 | S63: 27034 | T63: =IF(AND(ISNUMBER(S63),Q63>0),S63/Q63,"") -> 0.33604734 | U63: =IF(AND(ISNUMBER(O63),O63>0),100446/O63,"") -> 0.81551364 | V63: 1971 | W63: 99478 | Z63: Annual homes sold not populated — source: Redfin Data Center county-level housing market download (homes sold, monthly); record period when filled; Investor purchase share not populated — Redfin/ATTOM investor data uses metro definitions; store only if the geography matches this row, else leave blank and note the metro figure in Rationale | AA63: US Census Bureau ACS via Census Reporter | AB63: ACS 2024 5-year (2020–2024) | AC63: https://censusreporter.org/profiles/05000US36027/ | AE63: https://www.clearedgehomebuyers.com/locations/new-york/dutchess-county | AF63: /locations/new-york | AG63: Poughkeepsie, Beacon, Wappingers Falls
A64: NY | B64: Westchester & Hudson Valley | C64: Ulster County | D64: 36111 | E64: Ulster County, NY | F64: page | H64: Tier 3 | I64: Rural-suburban; state-hub coverage | J64: Not scheduled | K64: CMS record only | L64: Record only — covered by state hub; no page scheduled | M64: 182601 | N64: 352500 | O64: 86503 | P64: 74278 | Q64: 51924 | R64: =IF(AND(ISNUMBER(Q64),P64>0),Q64/P64,"") -> 0.69904952 | S64: 19398 | T64: =IF(AND(ISNUMBER(S64),Q64>0),S64/Q64,"") -> 0.37358447 | U64: =IF(AND(ISNUMBER(O64),O64>0),72775/O64,"") -> 0.8413003 | V64: 1966 | W64: 86271 | Z64: Annual homes sold not populated — source: Redfin Data Center county-level housing market download (homes sold, monthly); record period when filled; Investor purchase share not populated — Redfin/ATTOM investor data uses metro definitions; store only if the geography matches this row, else leave blank and note the metro figure in Rationale | AA64: US Census Bureau ACS via Census Reporter | AB64: ACS 2024 5-year (2020–2024) | AC64: https://censusreporter.org/profiles/05000US36111/ | AF64: /locations/new-york
A65: NY | B65: Westchester & Hudson Valley | C65: Sullivan County | D65: 36105 | E65: Sullivan County, NY | F65: page | H65: Tier 3 | I65: Rural; state-hub coverage | J65: Not scheduled | K65: CMS record only | L65: Record only — covered by state hub; no page scheduled | M65: 79721 | N65: 249000 | O65: 49994 | P65: 31434 | Q65: 21178 | R65: =IF(AND(ISNUMBER(Q65),P65>0),Q65/P65,"") -> 0.67372908 | S65: 8077 | T65: =IF(AND(ISNUMBER(S65),Q65>0),S65/Q65,"") -> 0.38138634 | U65: =IF(AND(ISNUMBER(O65),O65>0),41945/O65,"") -> 0.83900068 | V65: 1974 | W65: 72382 | Z65: Annual homes sold not populated — source: Redfin Data Center county-level housing market download (homes sold, monthly); record period when filled; Investor purchase share not populated — Redfin/ATTOM investor data uses metro definitions; store only if the geography matches this row, else leave blank and note the metro figure in Rationale | AA65: US Census Bureau ACS via Census Reporter | AB65: ACS 2024 5-year (2020–2024) | AC65: https://censusreporter.org/profiles/05000US36105/ | AF65: /locations/new-york
A66: NY | B66: Westchester & Hudson Valley | C66: Columbia County | D66: 36021 | E66: Columbia County, NY | F66: page | H66: Tier 3 | I66: Rural; state-hub coverage | J66: Not scheduled | K66: CMS record only | L66: Record only — covered by state hub; no page scheduled | M66: 61100 | N66: 347100 | O66: 33393 | P66: 26627 | Q66: 20315 | R66: =IF(AND(ISNUMBER(Q66),P66>0),Q66/P66,"") -> 0.76294738 | S66: 8392 | T66: =IF(AND(ISNUMBER(S66),Q66>0),S66/Q66,"") -> 0.41309377 | U66: =IF(AND(ISNUMBER(O66),O66>0),28734/O66,"") -> 0.86047974 | V66: 1966 | W66: 81528 | Z66: Annual homes sold not populated — source: Redfin Data Center county-level housing market download (homes sold, monthly); record period when filled; Investor purchase share not populated — Redfin/ATTOM investor data uses metro definitions; store only if the geography matches this row, else leave blank and note the metro figure in Rationale | AA66: US Census Bureau ACS via Census Reporter | AB66: ACS 2024 5-year (2020–2024) | AC66: https://censusreporter.org/profiles/05000US36021/ | AF66: /locations/new-york
A67: NY | B67: Westchester & Hudson Valley | C67: Greene County | D67: 36039 | E67: Greene County, NY | F67: page | H67: Tier 3 | I67: Rural; state-hub coverage | J67: Not scheduled | K67: CMS record only | L67: Record only — covered by state hub; no page scheduled | M67: 47409 | N67: 271600 | O67: 29080 | P67: 18674 | Q67: 14422 | R67: =IF(AND(ISNUMBER(Q67),P67>0),Q67/P67,"") -> 0.77230374 | S67: 5845 | T67: =IF(AND(ISNUMBER(S67),Q67>0),S67/Q67,"") -> 0.40528359 | U67: =IF(AND(ISNUMBER(O67),O67>0),25385/O67,"") -> 0.87293673 | V67: 1972 | W67: 77945 | Z67: Annual homes sold not populated — source: Redfin Data Center county-level housing market download (homes sold, monthly); record period when filled; Investor purchase share not populated — Redfin/ATTOM investor data uses metro definitions; store only if the geography matches this row, else leave blank and note the metro figure in Rationale | AA67: US Census Bureau ACS via Census Reporter | AB67: ACS 2024 5-year (2020–2024) | AC67: https://censusreporter.org/profiles/05000US36039/ | AF67: /locations/new-york
A68: CT | B68: Southern CT | C68: Western Connecticut Planning Region (legacy Fairfield/Litchfield) | D68: 09190 | E68: Western Connecticut Planning Region, CT | F68: statistical | G68: Attaches to hub: Fairfield County | I68: Stamford/Norwalk/Danbury corridor; highest CT values | K68: Statistical record only (no page) | L68: Never published; supplies market evidence to the hub named in column G | M68: 627071 | N68: 652900 | O68: 251530 | P68: 235379 | Q68: 156319 | R68: =IF(AND(ISNUMBER(Q68),P68>0),Q68/P68,"") -> 0.66411617 | S68: 50115 | T68: =IF(AND(ISNUMBER(S68),Q68>0),S68/Q68,"") -> 0.32059443 | U68: =IF(AND(ISNUMBER(O68),O68>0),192875/O68,"") -> 0.76680714 | V68: 1971 | W68: 128188 | Z68: Planning-region boundaries differ from legacy county boundaries (Census publishes relationship files); Annual homes sold not populated — source: Redfin Data Center county-level housing market download (homes sold, monthly); record period when filled; Investor purchase share not populated — Redfin/ATTOM investor data uses metro definitions; store only if the geography matches this row, else leave blank and note the metro figure in Rationale | AA68: US Census Bureau ACS via Census Reporter | AB68: ACS 2024 5-year (2020–2024) | AC68: https://censusreporter.org/profiles/05000US09190/
A69: CT | B69: Southern CT | C69: Greater Bridgeport Planning Region (legacy Fairfield) | D69: 09120 | E69: Greater Bridgeport Planning Region, CT | F69: statistical | G69: Attaches to hub: Fairfield County | I69: Bridgeport investor volume plus Stratford/Trumbull suburbs | K69: Statistical record only (no page) | L69: Never published; supplies market evidence to the hub named in column G | M69: 329259 | N69: 428800 | O69: 126039 | P69: 119633 | Q69: 78087 | R69: =IF(AND(ISNUMBER(Q69),P69>0),Q69/P69,"") -> 0.65272124 | S69: 25057 | T69: =IF(AND(ISNUMBER(S69),Q69>0),S69/Q69,"") -> 0.32088568 | U69: =IF(AND(ISNUMBER(O69),O69>0),104065/O69,"") -> 0.82565714 | V69: 1959 | W69: 89667 | Z69: Planning-region boundaries differ from legacy county boundaries (Census publishes relationship files); Annual homes sold not populated — source: Redfin Data Center county-level housing market download (homes sold, monthly); record period when filled; Investor purchase share not populated — Redfin/ATTOM investor data uses metro definitions; store only if the geography matches this row, else leave blank and note the metro figure in Rationale | AA69: US Census Bureau ACS via Census Reporter | AB69: ACS 2024 5-year (2020–2024) | AC69: https://censusreporter.org/profiles/05000US09120/
A70: CT | B70: Southern CT | C70: South Central Connecticut Planning Region (legacy New Haven) | D70: 09170 | E70: South Central Connecticut Planning Region, CT | F70: statistical | G70: Attaches to hub: New Haven County | I70: New Haven metro; mid values, active investors | K70: Statistical record only (no page) | L70: Never published; supplies market evidence to the hub named in column G | M70: 570598 | N70: 353100 | O70: 248267 | P70: 230673 | Q70: 139620 | R70: =IF(AND(ISNUMBER(Q70),P70>0),Q70/P70,"") -> 0.6052724 | S70: 47564 | T70: =IF(AND(ISNUMBER(S70),Q70>0),S70/Q70,"") -> 0.34066753 | U70: =IF(AND(ISNUMBER(O70),O70>0),193156/O70,"") -> 0.77801722 | V70: 1964 | W70: 88197 | Z70: Planning-region boundaries differ from legacy county boundaries (Census publishes relationship files); Annual homes sold not populated — source: Redfin Data Center county-level housing market download (homes sold, monthly); record period when filled; Investor purchase share not populated — Redfin/ATTOM investor data uses metro definitions; store only if the geography matches this row, else leave blank and note the metro figure in Rationale | AA70: US Census Bureau ACS via Census Reporter | AB70: ACS 2024 5-year (2020–2024) | AC70: https://censusreporter.org/profiles/05000US09170/
A71: CT | B71: Southern CT | C71: Naugatuck Valley Planning Region (legacy New Haven/Litchfield) | D71: 09140 | E71: Naugatuck Valley Planning Region, CT | F71: statistical | G71: Attaches to hub: New Haven County | I71: Waterbury; low values, high distress volume | K71: Statistical record only (no page) | L71: Never published; supplies market evidence to the hub named in column G | M71: 454969 | N71: 317700 | O71: 192551 | P71: 180116 | Q71: 123476 | R71: =IF(AND(ISNUMBER(Q71),P71>0),Q71/P71,"") -> 0.68553599 | S71: 40206 | T71: =IF(AND(ISNUMBER(S71),Q71>0),S71/Q71,"") -> 0.32561793 | U71: =IF(AND(ISNUMBER(O71),O71>0),161423/O71,"") -> 0.83833893 | V71: 1969 | W71: 86191 | Z71: Planning-region boundaries differ from legacy county boundaries (Census publishes relationship files); Annual homes sold not populated — source: Redfin Data Center county-level housing market download (homes sold, monthly); record period when filled; Investor purchase share not populated — Redfin/ATTOM investor data uses metro definitions; store only if the geography matches this row, else leave blank and note the metro figure in Rationale | AA71: US Census Bureau ACS via Census Reporter | AB71: ACS 2024 5-year (2020–2024) | AC71: https://censusreporter.org/profiles/05000US09140/
A72: CT | B72: Southern CT | C72: Lower Connecticut River Valley Planning Region (legacy Middlesex) | D72: 09130 | E72: Lower Connecticut River Valley Planning Region, CT | F72: statistical | G72: Attaches to hub: Middlesex County | I72: Shoreline; smaller volume | K72: Statistical record only (no page) | L72: Never published; supplies market evidence to the hub named in column G | M72: 175822 | N72: 379700 | O72: 82963 | P72: 74068 | Q72: 56136 | R72: =IF(AND(ISNUMBER(Q72),P72>0),Q72/P72,"") -> 0.75789815 | S72: 19380 | T72: =IF(AND(ISNUMBER(S72),Q72>0),S72/Q72,"") -> 0.34523301 | U72: =IF(AND(ISNUMBER(O72),O72>0),71588/O72,"") -> 0.86289069 | V72: 1972 | W72: 104428 | Z72: Planning-region boundaries differ from legacy county boundaries (Census publishes relationship files); Annual homes sold not populated — source: Redfin Data Center county-level housing market download (homes sold, monthly); record period when filled; Investor purchase share not populated — Redfin/ATTOM investor data uses metro definitions; store only if the geography matches this row, else leave blank and note the metro figure in Rationale | AA72: US Census Bureau ACS via Census Reporter | AB72: ACS 2024 5-year (2020–2024) | AC72: https://censusreporter.org/profiles/05000US09130/
A73: CT | B73: Southern CT | C73: Southeastern Connecticut Planning Region (legacy New London) | D73: 09180 | E73: Southeastern Connecticut Planning Region, CT | F73: statistical | G73: Attaches to hub: New London County | I73: New London/Norwich; mid-to-low values | K73: Statistical record only (no page) | L73: Never published; supplies market evidence to the hub named in column G | M73: 279971 | N73: 323400 | O73: 126425 | P73: 115768 | Q73: 75341 | R73: =IF(AND(ISNUMBER(Q73),P73>0),Q73/P73,"") -> 0.65079297 | S73: 26497 | T73: =IF(AND(ISNUMBER(S73),Q73>0),S73/Q73,"") -> 0.3516943 | U73: =IF(AND(ISNUMBER(O73),O73>0),103151/O73,"") -> 0.81590666 | V73: 1969 | W73: 86586 | Z73: Planning-region boundaries differ from legacy county boundaries (Census publishes relationship files); Annual homes sold not populated — source: Redfin Data Center county-level housing market download (homes sold, monthly); record period when filled; Investor purchase share not populated — Redfin/ATTOM investor data uses metro definitions; store only if the geography matches this row, else leave blank and note the metro figure in Rationale | AA73: US Census Bureau ACS via Census Reporter | AB73: ACS 2024 5-year (2020–2024) | AC73: https://censusreporter.org/profiles/05000US09180/
A74: CT | B74: Central CT | C74: Capitol Planning Region (legacy Hartford) | D74: 09110 | E74: Capitol Planning Region, CT | F74: statistical | G74: Attaches to hub: Hartford County | I74: Hartford metro; separate expansion decision per plan | K74: Statistical record only (no page) | L74: Never published; supplies market evidence to the hub named in column G | M74: 977290 | N74: 323700 | O74: 416559 | P74: 391113 | Q74: 257054 | R74: =IF(AND(ISNUMBER(Q74),P74>0),Q74/P74,"") -> 0.65723717 | S74: 82211 | T74: =IF(AND(ISNUMBER(S74),Q74>0),S74/Q74,"") -> 0.31981996 | U74: =IF(AND(ISNUMBER(O74),O74>0),327816/O74,"") -> 0.78696175 | V74: 1966 | W74: 93394 | Z74: Planning-region boundaries differ from legacy county boundaries (Census publishes relationship files); Annual homes sold not populated — source: Redfin Data Center county-level housing market download (homes sold, monthly); record period when filled; Investor purchase share not populated — Redfin/ATTOM investor data uses metro definitions; store only if the geography matches this row, else leave blank and note the metro figure in Rationale | AA74: US Census Bureau ACS via Census Reporter | AB74: ACS 2024 5-year (2020–2024) | AC74: https://censusreporter.org/profiles/05000US09110/
A75: CT | B75: Northern CT | C75: Northwest Hills Planning Region (legacy Litchfield) | D75: 09160 | E75: Northwest Hills Planning Region, CT | F75: statistical | G75: Attaches to hub: Litchfield County | I75: Rural; state-hub coverage | K75: Statistical record only (no page) | L75: Never published; supplies market evidence to the hub named in column G | M75: 113216 | N75: 335600 | O75: 55752 | P75: 47845 | Q75: 36503 | R75: =IF(AND(ISNUMBER(Q75),P75>0),Q75/P75,"") -> 0.76294284 | S75: 13006 | T75: =IF(AND(ISNUMBER(S75),Q75>0),S75/Q75,"") -> 0.35629948 | U75: =IF(AND(ISNUMBER(O75),O75>0),51200/O75,"") -> 0.9183527 | V75: 1967 | W75: 93551 | Z75: Planning-region boundaries differ from legacy county boundaries (Census publishes relationship files); Annual homes sold not populated — source: Redfin Data Center county-level housing market download (homes sold, monthly); record period when filled; Investor purchase share not populated — Redfin/ATTOM investor data uses metro definitions; store only if the geography matches this row, else leave blank and note the metro figure in Rationale | AA75: US Census Bureau ACS via Census Reporter | AB75: ACS 2024 5-year (2020–2024) | AC75: https://censusreporter.org/profiles/05000US09160/
A76: CT | B76: Northern CT | C76: Northeastern Connecticut Planning Region (legacy Windham/Tolland) | D76: 09150 | E76: Northeastern Connecticut Planning Region, CT | F76: statistical | G76: Attaches to hub: Windham County / Tolland County | I76: Rural; state-hub coverage | K76: Statistical record only (no page) | L76: Never published; supplies market evidence to the hub named in column G | M76: 96312 | N76: 307600 | O76: 41736 | P76: 39412 | Q76: 30453 | R76: =IF(AND(ISNUMBER(Q76),P76>0),Q76/P76,"") -> 0.77268345 | S76: 9092 | T76: =IF(AND(ISNUMBER(S76),Q76>0),S76/Q76,"") -> 0.29855843 | U76: =IF(AND(ISNUMBER(O76),O76>0),37687/O76,"") -> 0.90298543 | V76: 1973 | W76: 90589 | Z76: Planning-region boundaries differ from legacy county boundaries (Census publishes relationship files); Annual homes sold not populated — source: Redfin Data Center county-level housing market download (homes sold, monthly); record period when filled; Investor purchase share not populated — Redfin/ATTOM investor data uses metro definitions; store only if the geography matches this row, else leave blank and note the metro figure in Rationale | AA76: US Census Bureau ACS via Census Reporter | AB76: ACS 2024 5-year (2020–2024) | AC76: https://censusreporter.org/profiles/05000US09150/
A77: CT | B77: Southern CT | C77: Fairfield County | D77: 09001 | F77: page | G77: Statistical areas: 09190; 09120 | H77: Tier 1 | I77: Stamford/Norwalk/Danbury/Bridgeport corridor; highest CT values | J77: Wave 4 | K77: New hub | L77: Wave 4: publish county/borough hub; city pages only where demand verified | Z77: No county-level ACS figures: Census reports CT by planning region; read the attached statistical rows and cite them as planning-region figures — never average or relabel as county medians; Annual homes sold not populated — source: Redfin Data Center county-level housing market download (homes sold, monthly); record period when filled; Investor purchase share not populated — Redfin/ATTOM investor data uses metro definitions; store only if the geography matches this row, else leave blank and note the metro figure in Rationale | AE77: https://www.clearedgehomebuyers.com/locations/connecticut/fairfield-county | AF77: /locations/connecticut | AG77: Bridgeport, Stamford, Norwalk, Danbury, Stratford
A78: CT | B78: Southern CT | C78: New Haven County | D78: 09009 | F78: page | G78: Statistical areas: 09170; 09140 | H78: Tier 2 | I78: New Haven and Waterbury metros; mid values, active investors | J78: Wave 5 | K78: New hub | L78: Wave 5: publish county/borough hub; city pages only where demand verified | Z78: No county-level ACS figures: Census reports CT by planning region; read the attached statistical rows and cite them as planning-region figures — never average or relabel as county medians; Annual homes sold not populated — source: Redfin Data Center county-level housing market download (homes sold, monthly); record period when filled; Investor purchase share not populated — Redfin/ATTOM investor data uses metro definitions; store only if the geography matches this row, else leave blank and note the metro figure in Rationale | AE78: https://www.clearedgehomebuyers.com/locations/connecticut/new-haven-county | AF78: /locations/connecticut | AG78: New Haven, Waterbury, Hamden, West Haven, Meriden
A79: CT | B79: Southern CT | C79: Middlesex County | D79: 09007 | F79: page | G79: Statistical areas: 09130 | H79: Tier 2 | I79: Shoreline; smaller volume | J79: Wave 5 | K79: New hub | L79: Wave 5: publish county/borough hub; city pages only where demand verified | Z79: No county-level ACS figures: Census reports CT by planning region; read the attached statistical rows and cite them as planning-region figures — never average or relabel as county medians; Annual homes sold not populated — source: Redfin Data Center county-level housing market download (homes sold, monthly); record period when filled; Investor purchase share not populated — Redfin/ATTOM investor data uses metro definitions; store only if the geography matches this row, else leave blank and note the metro figure in Rationale | AE79: https://www.clearedgehomebuyers.com/locations/connecticut/middlesex-county | AF79: /locations/connecticut | AG79: Middletown
A80: CT | B80: Southern CT | C80: New London County | D80: 09011 | F80: page | G80: Statistical areas: 09180 | H80: Tier 2 | I80: New London/Norwich; mid-to-low values | J80: Wave 5 | K80: New hub | L80: Wave 5: publish county/borough hub; city pages only where demand verified | Z80: No county-level ACS figures: Census reports CT by planning region; read the attached statistical rows and cite them as planning-region figures — never average or relabel as county medians; Annual homes sold not populated — source: Redfin Data Center county-level housing market download (homes sold, monthly); record period when filled; Investor purchase share not populated — Redfin/ATTOM investor data uses metro definitions; store only if the geography matches this row, else leave blank and note the metro figure in Rationale | AE80: https://www.clearedgehomebuyers.com/locations/connecticut/new-london-county | AF80: /locations/connecticut | AG80: New London, Norwich
A81: CT | B81: Central CT | C81: Hartford County | D81: 09003 | F81: page | G81: Statistical areas: 09110 | H81: Tier 2 | I81: Hartford metro; separate expansion decision per plan | J81: Wave 5 | K81: New hub | L81: Wave 5: publish county/borough hub; city pages only where demand verified | Z81: No county-level ACS figures: Census reports CT by planning region; read the attached statistical rows and cite them as planning-region figures — never average or relabel as county medians; Annual homes sold not populated — source: Redfin Data Center county-level housing market download (homes sold, monthly); record period when filled; Investor purchase share not populated — Redfin/ATTOM investor data uses metro definitions; store only if the geography matches this row, else leave blank and note the metro figure in Rationale | AE81: https://www.clearedgehomebuyers.com/locations/connecticut/hartford-county | AF81: /locations/connecticut | AG81: Hartford, New Britain, Bristol
A82: CT | B82: Northern CT | C82: Litchfield County | D82: 09005 | F82: page | G82: Statistical areas: 09160; 09190 (part) | H82: Tier 3 | I82: Rural; state-hub coverage | J82: Not scheduled | K82: CMS record only | L82: Record only — covered by state hub; no page scheduled | Z82: No county-level ACS figures: Census reports CT by planning region; read the attached statistical rows and cite them as planning-region figures — never average or relabel as county medians; Annual homes sold not populated — source: Redfin Data Center county-level housing market download (homes sold, monthly); record period when filled; Investor purchase share not populated — Redfin/ATTOM investor data uses metro definitions; store only if the geography matches this row, else leave blank and note the metro figure in Rationale | AF82: /locations/connecticut
A83: CT | B83: Northern CT | C83: Tolland County | D83: 09013 | F83: page | G83: Statistical areas: 09150; 09110 (part) | H83: Tier 3 | I83: Rural; state-hub coverage | J83: Not scheduled | K83: CMS record only | L83: Record only — covered by state hub; no page scheduled | Z83: No county-level ACS figures: Census reports CT by planning region; read the attached statistical rows and cite them as planning-region figures — never average or relabel as county medians; Annual homes sold not populated — source: Redfin Data Center county-level housing market download (homes sold, monthly); record period when filled; Investor purchase share not populated — Redfin/ATTOM investor data uses metro definitions; store only if the geography matches this row, else leave blank and note the metro figure in Rationale | AF83: /locations/connecticut
A84: CT | B84: Northern CT | C84: Windham County | D84: 09015 | F84: page | G84: Statistical areas: 09150 | H84: Tier 3 | I84: Rural; state-hub coverage | J84: Not scheduled | K84: CMS record only | L84: Record only — covered by state hub; no page scheduled | Z84: No county-level ACS figures: Census reports CT by planning region; read the attached statistical rows and cite them as planning-region figures — never average or relabel as county medians; Annual homes sold not populated — source: Redfin Data Center county-level housing market download (homes sold, monthly); record period when filled; Investor purchase share not populated — Redfin/ATTOM investor data uses metro definitions; store only if the geography matches this row, else leave blank and note the metro figure in Rationale | AF84: /locations/connecticut

Sheet Summary
A1: Tier (page records only) | B1: Counties / boroughs | C1: Wave 1 | D1: Wave 2 | E1: Wave 3 | F1: Wave 4 | G1: Wave 5 | H1: Not scheduled
A2: Existing core | B2: =COUNTIFS(Inventory!$H$3:$H$200,A2,Inventory!$F$3:$F$200,"page") -> 9 | C2: =COUNTIFS(Inventory!$H$3:$H$200,$A2,Inventory!$J$3:$J$200,C$1,Inventory!$F$3:$F$200,"page") -> 9 | D2: =COUNTIFS(Inventory!$H$3:$H$200,$A2,Inventory!$J$3:$J$200,D$1,Inventory!$F$3:$F$200,"page") -> 0 | E2: =COUNTIFS(Inventory!$H$3:$H$200,$A2,Inventory!$J$3:$J$200,E$1,Inventory!$F$3:$F$200,"page") -> 0 | F2: =COUNTIFS(Inventory!$H$3:$H$200,$A2,Inventory!$J$3:$J$200,F$1,Inventory!$F$3:$F$200,"page") -> 0 | G2: =COUNTIFS(Inventory!$H$3:$H$200,$A2,Inventory!$J$3:$J$200,G$1,Inventory!$F$3:$F$200,"page") -> 0 | H2: =COUNTIFS(Inventory!$H$3:$H$200,$A2,Inventory!$J$3:$J$200,H$1,Inventory!$F$3:$F$200,"page") -> 0
A3: Tier 1 | B3: =COUNTIFS(Inventory!$H$3:$H$200,A3,Inventory!$F$3:$F$200,"page") -> 22 | C3: =COUNTIFS(Inventory!$H$3:$H$200,$A3,Inventory!$J$3:$J$200,C$1,Inventory!$F$3:$F$200,"page") -> 5 | D3: =COUNTIFS(Inventory!$H$3:$H$200,$A3,Inventory!$J$3:$J$200,D$1,Inventory!$F$3:$F$200,"page") -> 8 | E3: =COUNTIFS(Inventory!$H$3:$H$200,$A3,Inventory!$J$3:$J$200,E$1,Inventory!$F$3:$F$200,"page") -> 8 | F3: =COUNTIFS(Inventory!$H$3:$H$200,$A3,Inventory!$J$3:$J$200,F$1,Inventory!$F$3:$F$200,"page") -> 1 | G3: =COUNTIFS(Inventory!$H$3:$H$200,$A3,Inventory!$J$3:$J$200,G$1,Inventory!$F$3:$F$200,"page") -> 0 | H3: =COUNTIFS(Inventory!$H$3:$H$200,$A3,Inventory!$J$3:$J$200,H$1,Inventory!$F$3:$F$200,"page") -> 0
A4: Tier 2 | B4: =COUNTIFS(Inventory!$H$3:$H$200,A4,Inventory!$F$3:$F$200,"page") -> 19 | C4: =COUNTIFS(Inventory!$H$3:$H$200,$A4,Inventory!$J$3:$J$200,C$1,Inventory!$F$3:$F$200,"page") -> 0 | D4: =COUNTIFS(Inventory!$H$3:$H$200,$A4,Inventory!$J$3:$J$200,D$1,Inventory!$F$3:$F$200,"page") -> 0 | E4: =COUNTIFS(Inventory!$H$3:$H$200,$A4,Inventory!$J$3:$J$200,E$1,Inventory!$F$3:$F$200,"page") -> 0 | F4: =COUNTIFS(Inventory!$H$3:$H$200,$A4,Inventory!$J$3:$J$200,F$1,Inventory!$F$3:$F$200,"page") -> 0 | G4: =COUNTIFS(Inventory!$H$3:$H$200,$A4,Inventory!$J$3:$J$200,G$1,Inventory!$F$3:$F$200,"page") -> 19 | H4: =COUNTIFS(Inventory!$H$3:$H$200,$A4,Inventory!$J$3:$J$200,H$1,Inventory!$F$3:$F$200,"page") -> 0
A5: Tier 3 | B5: =COUNTIFS(Inventory!$H$3:$H$200,A5,Inventory!$F$3:$F$200,"page") -> 23 | C5: =COUNTIFS(Inventory!$H$3:$H$200,$A5,Inventory!$J$3:$J$200,C$1,Inventory!$F$3:$F$200,"page") -> 0 | D5: =COUNTIFS(Inventory!$H$3:$H$200,$A5,Inventory!$J$3:$J$200,D$1,Inventory!$F$3:$F$200,"page") -> 0 | E5: =COUNTIFS(Inventory!$H$3:$H$200,$A5,Inventory!$J$3:$J$200,E$1,Inventory!$F$3:$F$200,"page") -> 0 | F5: =COUNTIFS(Inventory!$H$3:$H$200,$A5,Inventory!$J$3:$J$200,F$1,Inventory!$F$3:$F$200,"page") -> 0 | G5: =COUNTIFS(Inventory!$H$3:$H$200,$A5,Inventory!$J$3:$J$200,G$1,Inventory!$F$3:$F$200,"page") -> 0 | H5: =COUNTIFS(Inventory!$H$3:$H$200,$A5,Inventory!$J$3:$J$200,H$1,Inventory!$F$3:$F$200,"page") -> 23
A6: Total page records | B6: =SUM(B2:B5) -> 73 | C6: =SUM(C2:C5) -> 14 | D6: =SUM(D2:D5) -> 8 | E6: =SUM(E2:E5) -> 8 | F6: =SUM(F2:F5) -> 1 | G6: =SUM(G2:G5) -> 19 | H6: =SUM(H2:H5) -> 23
A7: Statistical records (CT planning regions) | B7: =COUNTIF(Inventory!$F$3:$F$200,"statistical") -> 9
A9: State | B9: Page records | C9: Tier 1 | D9: Tier 2 | E9: Existing core | F9: Median of median home values, page records with ACS data ($)
A10: PA | B10: =COUNTIFS(Inventory!$A$3:$A$200,A10,Inventory!$F$3:$F$200,"page") -> 28 | C10: =COUNTIFS(Inventory!$A$3:$A$200,A10,Inventory!$H$3:$H$200,"Tier 1") -> 5 | D10: =COUNTIFS(Inventory!$A$3:$A$200,A10,Inventory!$H$3:$H$200,"Tier 2") -> 4 | E10: =COUNTIFS(Inventory!$A$3:$A$200,A10,Inventory!$H$3:$H$200,"Existing core") -> 9 | F10: {=IFERROR(MEDIAN(IF((Inventory!$A$3:$A$200=A10)*(Inventory!$F$3:$F$200="page")*ISNUMBER(Inventory!$N$3:$N$200),Inventory!$N$3:$N$200)),"n/a (planning-region data only)")} -> 245850
A11: NJ | B11: =COUNTIFS(Inventory!$A$3:$A$200,A11,Inventory!$F$3:$F$200,"page") -> 21 | C11: =COUNTIFS(Inventory!$A$3:$A$200,A11,Inventory!$H$3:$H$200,"Tier 1") -> 8 | D11: =COUNTIFS(Inventory!$A$3:$A$200,A11,Inventory!$H$3:$H$200,"Tier 2") -> 7 | E11: =COUNTIFS(Inventory!$A$3:$A$200,A11,Inventory!$H$3:$H$200,"Existing core") -> 0 | F11: {=IFERROR(MEDIAN(IF((Inventory!$A$3:$A$200=A11)*(Inventory!$F$3:$F$200="page")*ISNUMBER(Inventory!$N$3:$N$200),Inventory!$N$3:$N$200)),"n/a (planning-region data only)")} -> 434600
A12: NY | B12: =COUNTIFS(Inventory!$A$3:$A$200,A12,Inventory!$F$3:$F$200,"page") -> 16 | C12: =COUNTIFS(Inventory!$A$3:$A$200,A12,Inventory!$H$3:$H$200,"Tier 1") -> 8 | D12: =COUNTIFS(Inventory!$A$3:$A$200,A12,Inventory!$H$3:$H$200,"Tier 2") -> 4 | E12: =COUNTIFS(Inventory!$A$3:$A$200,A12,Inventory!$H$3:$H$200,"Existing core") -> 0 | F12: {=IFERROR(MEDIAN(IF((Inventory!$A$3:$A$200=A12)*(Inventory!$F$3:$F$200="page")*ISNUMBER(Inventory!$N$3:$N$200),Inventory!$N$3:$N$200)),"n/a (planning-region data only)")} -> 553950
A13: CT | B13: =COUNTIFS(Inventory!$A$3:$A$200,A13,Inventory!$F$3:$F$200,"page") -> 8 | C13: =COUNTIFS(Inventory!$A$3:$A$200,A13,Inventory!$H$3:$H$200,"Tier 1") -> 1 | D13: =COUNTIFS(Inventory!$A$3:$A$200,A13,Inventory!$H$3:$H$200,"Tier 2") -> 4 | E13: =COUNTIFS(Inventory!$A$3:$A$200,A13,Inventory!$H$3:$H$200,"Existing core") -> 0 | F13: {=IFERROR(MEDIAN(IF((Inventory!$A$3:$A$200=A13)*(Inventory!$F$3:$F$200="page")*ISNUMBER(Inventory!$N$3:$N$200),Inventory!$N$3:$N$200)),"n/a (planning-region data only)")} -> n/a (planning-region data only)

Sheet Legend & sources
A1: Field group | B1: Notes
A2: Record type | B2: page = a geography that can carry a public hub (one unique URL per page record). statistical = a Census geography that supplies figures to a page record and never renders. Connecticut is the only state with statistical rows: the Census Bureau reports CT by nine planning regions (county-equivalents since 2022), whose boundaries differ from the eight legacy counties. Each CT county page row names its attached planning regions in column G. Cite those figures as planning-region figures; never average them into a county median.
A3: Tier | B3: Existing core = pages already live in eastern PA. Tier 1 = full county/borough hub, situation×county pages where they earn it, selected city pages. Tier 2 = county hub + situation coverage, few or no city pages. Tier 3 = CMS record only; covered by the state hub; no page scheduled. Tiers are a research prior; adjust after the market-evidence columns are filled.
A4: Build wave | B4: Wave 0 (not in this sheet) = state hubs and geographic spine. Wave 1 = SE PA + attach existing PA pages. Wave 2 = North & Central NJ Tier 1. Wave 3 = NYC boroughs, Long Island, Westchester/Rockland. Wave 4 = Fairfield County CT. Wave 5 = Tier 2 fill across all states.
A5: Page status vs publish decision | B5: Every row gets a Sanity record regardless of tier. Publication is a separate decision recorded in the Publish decision column. Market priority never auto-publishes a page.
A6: Market evidence — populated | B6: Population (B01003), median owner-occupied home value (B25077), all housing units (B25001), occupied housing units (B25003_001), owner-occupied units (B25003_002), owner households by age of householder (B25007; 65+ = 65–74, 75–84, 85+), units in structure (B25024; 1–4 unit = 1 detached, 1 attached, 2, 3–4), median year built (B25035), median household income (B19013). US Census Bureau American Community Survey 2024 5-year estimates (2020–2024), retrieved via the Census Reporter API on 2026-09-26. Per-row Source URL links to the Census Reporter profile.
A7: Homeownership rate | B7: Owner-occupied units ÷ occupied housing units — the standard Census definition (vacant units excluded). marketSnapshot.ownerShare in Sanity uses this same definition.
A8: 1–4 unit share of all housing stock | B8: Units in 1-unit detached, 1-unit attached, 2-unit, or 3–4-unit structures ÷ all housing units (vacant included). The stock a cash buyer can actually purchase and assign. Low values (Manhattan, Hudson County, Bronx) signal co-op/condo/large-multifamily markets.
A9: Owners 65+ share | B9: Owner households with householder aged 65+ ÷ owner-occupied units. Proxy for inherited-property supply.
A10: Market evidence — not populated (yellow cells) | B10: Annual homes sold: available at county level from the Redfin Data Center housing-market downloads (https://www.redfin.com/news/data-center/); fill with the trailing-12-month figure and record the period. Investor purchase share: Redfin and ATTOM investor reports use metro or ZIP definitions, not counties; store a value only where the geography matches the row, otherwise leave blank and note the metro figure in Rationale.
A11: Existing URLs | B11: Pulled from the live sitemap (https://www.clearedgehomebuyers.com/sitemap.xml) on 2026-09-26: 62 URLs total = 22 location URLs (3 region hubs + 19 city pages), 9 situation pages, 20 blog articles, 11 core pages. /cashoffernj is not in the sitemap. Sitemap absence does not prove page absence: reconcile against Sanity and GSC before the preservation list is final. None of these URLs move.
A12: Proposed hub URL pattern | B12: /locations/<state>/<county>-county for counties; /locations/new-york/<borough> for boroughs; /locations/pennsylvania/philadelphia for Philadelphia. Existing region hubs (/locations/nepa, /locations/lehigh-valley, /locations/poconos) remain the parents for the counties they already cover.
A13: Editable cells | B13: Tier, Rationale, Build wave, Publish decision, Candidate pages, and the two yellow market-evidence columns are meant to be edited. Census columns should be refreshed from source rather than hand-edited.
